Workbook

Sheet Masterfile
A1: RTM | B1: PUB | C1: STREET | D1: VILLAGE | E1: TOWN | F1: COUNTY | G1: POSTCODE | H1: POST DISTRICT | I1: POST SECTOR | J1: RM | K1: STRATEGY | L1: Notes
A2: Greene King L&T | B2: Horse & Groom | C2: 20 Rayne Road | D2: Braintree | F2: Essex | G2: CM7 2QA | H2: =_xlfn.TEXTBEFORE(G2," ") -> CM7 | I2: {=LEFT(G2, MIN(IF(ISNUMBER(--MID(G2, _xlfn.SEQUENCE(LEN(G2)), 1)), _xlfn.SEQUENCE(LEN(G2)))) - 1)} -> CM | J2: James Pearson | K2: GROW - Stella/SM +1 | L2: Won San Miguel here a few months ago. Veronica running pub after her husband passed away but her duaghter Antionette really makes the decisions. Should be able to get more stuff here but is Tier 3
A3: Greene King IFT | B3: Tomos Tavern Limited | G3: CM7 2TH | H3: =_xlfn.TEXTBEFORE(G3," ") -> CM7 | I3: {=LEFT(G3, MIN(IF(ISNUMBER(--MID(G3, _xlfn.SEQUENCE(LEN(G3)), 1)), _xlfn.SEQUENCE(LEN(G3)))) - 1)} -> CM | J3: =_xlfn.XLOOKUP(H3,'GK IFT SDM POSTCODES'!A:A,'GK IFT SDM POSTCODES'!B:B,"") -> Nikki Hayter | K3: GET
A4: Greene King IFT | B4: Loft Tavern (Braintree) | G4: CM7 2TH | H4: =_xlfn.TEXTBEFORE(G4," ") -> CM7 | I4: {=LEFT(G4, MIN(IF(ISNUMBER(--MID(G4, _xlfn.SEQUENCE(LEN(G4)), 1)), _xlfn.SEQUENCE(LEN(G4)))) - 1)} -> CM | J4: =_xlfn.XLOOKUP(H4,'GK IFT SDM POSTCODES'!A:A,'GK IFT SDM POSTCODES'!B:B,"") -> Nikki Hayter | K4: GET
A5: Admiral | B5: Nags Head Wine Bar, Braintree | C5: 8 Market Place, | E5: Braintree | G5: CM7 3HG | H5: =_xlfn.TEXTBEFORE(G5," ") -> CM7 | I5: {=LEFT(G5, MIN(IF(ISNUMBER(--MID(G5, _xlfn.SEQUENCE(LEN(G5)), 1)), _xlfn.SEQUENCE(LEN(G5)))) - 1)} -> CM | J5: Nicky Bellingham | K5: GROW - Stella/SM +1 | L5: Proper Pubs. Stella on and good to support
A6: Greene King IFT | B6: Sportsman (Braintree) | G6: CM7 3QX | H6: =_xlfn.TEXTBEFORE(G6," ") -> CM7 | I6: {=LEFT(G6, MIN(IF(ISNUMBER(--MID(G6, _xlfn.SEQUENCE(LEN(G6)), 1)), _xlfn.SEQUENCE(LEN(G6)))) - 1)} -> CM | J6: =_xlfn.XLOOKUP(H6,'GK IFT SDM POSTCODES'!A:A,'GK IFT SDM POSTCODES'!B:B,"") -> Nikki Hayter | K6: GROW - Stella/SM +1 | L6: Small place with Stella on bar. Not much opps other than San Mig
A7: Greene King IFT | B7: Horse & Groom PH (Cornish Hall End) | G7: CM7 4HF | H7: =_xlfn.TEXTBEFORE(G7," ") -> CM7 | I7: {=LEFT(G7, MIN(IF(ISNUMBER(--MID(G7, _xlfn.SEQUENCE(LEN(G7)), 1)), _xlfn.SEQUENCE(LEN(G7)))) - 1)} -> CM | J7: =_xlfn.XLOOKUP(H7,'GK IFT SDM POSTCODES'!A:A,'GK IFT SDM POSTCODES'!B:B,"") -> Nikki Hayter | K7: GET
A8: Greene King IFT | B8: Vine (Great Bardfield) | G8: CM7 4SR | H8: =_xlfn.TEXTBEFORE(G8," ") -> CM7 | I8: {=LEFT(G8, MIN(IF(ISNUMBER(--MID(G8, _xlfn.SEQUENCE(LEN(G8)), 1)), _xlfn.SEQUENCE(LEN(G8)))) - 1)} -> CM | J8: =_xlfn.XLOOKUP(H8,'GK IFT SDM POSTCODES'!A:A,'GK IFT SDM POSTCODES'!B:B,"") -> Nikki Hayter | K8: GET | L8: good opps here for stella, More premium beers and lots fo POS around but could never get LL contact
A9: Greene King L&T | B9: Bell | C9: Kynaston Road | D9: Panfield | E9: Braintree | F9: Essex | G9: CM7 5AQ | H9: =_xlfn.TEXTBEFORE(G9," ") -> CM7 | I9: {=LEFT(G9, MIN(IF(ISNUMBER(--MID(G9, _xlfn.SEQUENCE(LEN(G9)), 1)), _xlfn.SEQUENCE(LEN(G9)))) - 1)} -> CM | J9: James Pearson | K9: GROW | L9: Went here with TNT a few times and was THIS close to a deal. Would never take Stella. Wanted Corona but JP dragged his feet on it. Right next to a football pitch so can do an outside bar. Family run pub but Dad and Son make decisions (cant remmeber names lol)
A10: Greene King IFT | B10: Bocking United Serv Social Club | G10: CM7 5LA | H10: =_xlfn.TEXTBEFORE(G10," ") -> CM7 | I10: {=LEFT(G10, MIN(IF(ISNUMBER(--MID(G10, _xlfn.SEQUENCE(LEN(G10)), 1)), _xlfn.SEQUENCE(LEN(G10)))) - 1)} -> CM | J10: =_xlfn.XLOOKUP(H10,'GK IFT SDM POSTCODES'!A:A,'GK IFT SDM POSTCODES'!B:B,"") -> Nikki Hayter | K10: GET | L10: HUK Smart Dispense so tricky one
A11: Greene King IFT | B11: Bocking Social Club Limited | G11: CM7 5LA | H11: =_xlfn.TEXTBEFORE(G11," ") -> CM7 | I11: {=LEFT(G11, MIN(IF(ISNUMBER(--MID(G11, _xlfn.SEQUENCE(LEN(G11)), 1)), _xlfn.SEQUENCE(LEN(G11)))) - 1)} -> CM | J11: =_xlfn.XLOOKUP(H11,'GK IFT SDM POSTCODES'!A:A,'GK IFT SDM POSTCODES'!B:B,"") -> Nikki Hayter | K11: GET | L11: HUK Smart Dispense so tricky one
A12: Greene King IFT | B12: O'Gradys (Braintree) | G12: CM7 5RL | H12: =_xlfn.TEXTBEFORE(G12," ") -> CM7 | I12: {=LEFT(G12, MIN(IF(ISNUMBER(--MID(G12, _xlfn.SEQUENCE(LEN(G12)), 1)), _xlfn.SEQUENCE(LEN(G12)))) - 1)} -> CM | J12: =_xlfn.XLOOKUP(H12,'GK IFT SDM POSTCODES'!A:A,'GK IFT SDM POSTCODES'!B:B,"") -> Nikki Hayter | K12: KEEP | L12: Don't bother
A13: Admiral | B13: Eagle, Braintree | C13: 192 Coggeshall Road, | E13: Braintree | G13: CM7 9ER | H13: =_xlfn.TEXTBEFORE(G13," ") -> CM7 | I13: {=LEFT(G13, MIN(IF(ISNUMBER(--MID(G13, _xlfn.SEQUENCE(LEN(G13)), 1)), _xlfn.SEQUENCE(LEN(G13)))) - 1)} -> CM | J13: Nicky Bellingham | K13: GROW - Stella/SM +1 | L13: Proper Pubs. Stella on and good to support
A14: Greene King IFT | B14: Swiss Bell (Braintree) | G14: CM7 9UL | H14: =_xlfn.TEXTBEFORE(G14," ") -> CM7 | I14: {=LEFT(G14, MIN(IF(ISNUMBER(--MID(G14, _xlfn.SEQUENCE(LEN(G14)), 1)), _xlfn.SEQUENCE(LEN(G14)))) - 1)} -> CM | J14: =_xlfn.XLOOKUP(H14,'GK IFT SDM POSTCODES'!A:A,'GK IFT SDM POSTCODES'!B:B,"") -> Nikki Hayter | K14: GET
A15: Admiral | B15: Welsh Princess, Rayne | C15: 21 The Street, Braintree | E15: Rayne | G15: CM77 6RW | H15: =_xlfn.TEXTBEFORE(G15," ") -> CM77 | I15: {=LEFT(G15, MIN(IF(ISNUMBER(--MID(G15, _xlfn.SEQUENCE(LEN(G15)), 1)), _xlfn.SEQUENCE(LEN(G15)))) - 1)} -> CM | J15: James McIver | K15: GET | L15: Was closed for most of my time with it but may be reopen
A16: Greene King IFT | B16: Braintree Golf Club (Braintree) | G16: CM77 8DD | H16: =_xlfn.TEXTBEFORE(G16," ") -> CM77 | I16: {=LEFT(G16, MIN(IF(ISNUMBER(--MID(G16, _xlfn.SEQUENCE(LEN(G16)), 1)), _xlfn.SEQUENCE(LEN(G16)))) - 1)} -> CM | J16: =_xlfn.XLOOKUP(H16,'GK IFT SDM POSTCODES'!A:A,'GK IFT SDM POSTCODES'!B:B,"") -> Nikki Hayter | K16: GET | L16: CMBC direct. Buys ales through GK so Neil Stebbing will wnt to increase distro. San Mig was on before they took it off
A17: Greene King IFT | B17: Black Notley Community Association | G17: CM77 8NE | H17: =_xlfn.TEXTBEFORE(G17," ") -> CM77 | I17: {=LEFT(G17, MIN(IF(ISNUMBER(--MID(G17, _xlfn.SEQUENCE(LEN(G17)), 1)), _xlfn.SEQUENCE(LEN(G17)))) - 1)} -> CM | J17: =_xlfn.XLOOKUP(H17,'GK IFT SDM POSTCODES'!A:A,'GK IFT SDM POSTCODES'!B:B,"") -> Nikki Hayter | K17: GROW - Stella/SM +1
A18: Greene King IFT | B18: Swan (Witham) | G18: CM8 1BE | H18: =_xlfn.TEXTBEFORE(G18," ") -> CM8 | I18: {=LEFT(G18, MIN(IF(ISNUMBER(--MID(G18, _xlfn.SEQUENCE(LEN(G18)), 1)), _xlfn.SEQUENCE(LEN(G18)))) - 1)} -> CM | J18: =_xlfn.XLOOKUP(H18,'GK IFT SDM POSTCODES'!A:A,'GK IFT SDM POSTCODES'!B:B,"") -> Neil Stebbings | K18: GROW - Stella/SM +1 | L18: good opps for San Mig but LL never in
A19: Greene King IFT | B19: RAFA Witham & Rivenhall Club | G19: CM8 1BX | H19: =_xlfn.TEXTBEFORE(G19," ") -> CM8 | I19: {=LEFT(G19, MIN(IF(ISNUMBER(--MID(G19, _xlfn.SEQUENCE(LEN(G19)), 1)), _xlfn.SEQUENCE(LEN(G19)))) - 1)} -> CM | J19: =_xlfn.XLOOKUP(H19,'GK IFT SDM POSTCODES'!A:A,'GK IFT SDM POSTCODES'!B:B,"") -> Neil Stebbings | K19: GROW - Stella/SM +1 | L19: Good opps for San Mig. Stella on and does well but small vols
A20: Greene King IFT | B20: White Notley FC (Faulkebourne) | G20: CM8 1SF | H20: =_xlfn.TEXTBEFORE(G20," ") -> CM8 | I20: {=LEFT(G20, MIN(IF(ISNUMBER(--MID(G20, _xlfn.SEQUENCE(LEN(G20)), 1)), _xlfn.SEQUENCE(LEN(G20)))) - 1)} -> CM | J20: =_xlfn.XLOOKUP(H20,'GK IFT SDM POSTCODES'!A:A,'GK IFT SDM POSTCODES'!B:B,"") -> Neil Stebbings | K20: GET
A21: Greene King L&T | B21: White Hart | C21: Newland Street | D21: Witham | F21: Essex | G21: CM8 2AF | H21: =_xlfn.TEXTBEFORE(G21," ") -> CM8 | I21: {=LEFT(G21, MIN(IF(ISNUMBER(--MID(G21, _xlfn.SEQUENCE(LEN(G21)), 1)), _xlfn.SEQUENCE(LEN(G21)))) - 1)} -> CM | J21: James Pearson | K21: GROW - Stella/SM +1
A22: Admiral | B22: George, Witham | C22: 36 Newland Street, | E22: Witham | G22: CM8 2AQ | H22: =_xlfn.TEXTBEFORE(G22," ") -> CM8 | I22: {=LEFT(G22, MIN(IF(ISNUMBER(--MID(G22, _xlfn.SEQUENCE(LEN(G22)), 1)), _xlfn.SEQUENCE(LEN(G22)))) - 1)} -> CM | J22: Troy Bett | K22: GROW - Stella/SM +1 | L22: Recently reopened and have installed Stella (already claimed W sorry)
A23: Greene King IFT | B23: Spring Lodge Community Centre | G23: CM8 2HE | H23: =_xlfn.TEXTBEFORE(G23," ") -> CM8 | I23: {=LEFT(G23, MIN(IF(ISNUMBER(--MID(G23, _xlfn.SEQUENCE(LEN(G23)), 1)), _xlfn.SEQUENCE(LEN(G23)))) - 1)} -> CM | J23: =_xlfn.XLOOKUP(H23,'GK IFT SDM POSTCODES'!A:A,'GK IFT SDM POSTCODES'!B:B,"") -> Neil Stebbings | K23: GET | L23: Laura bar personl. Good opps for Stella andSan Mig but they are reluctant to change
A24: Admiral | B24: White Horse, Witham | C24: 2 Church Street, | E24: Witham | G24: CM8 2JL | H24: =_xlfn.TEXTBEFORE(G24," ") -> CM8 | I24: {=LEFT(G24, MIN(IF(ISNUMBER(--MID(G24, _xlfn.SEQUENCE(LEN(G24)), 1)), _xlfn.SEQUENCE(LEN(G24)))) - 1)} -> CM | J24: Troy Bett | K24: GROW - Stella/SM +1 | L24: Part of MO that has two on my patch. Pale in all of them. We've got good opps to do Mahou, Stella in all three so lets team up on this
A25: Greene King IFT | B25: Woolpack Inn (Witham) | G25: CM8 2JP | H25: =_xlfn.TEXTBEFORE(G25," ") -> CM8 | I25: {=LEFT(G25, MIN(IF(ISNUMBER(--MID(G25, _xlfn.SEQUENCE(LEN(G25)), 1)), _xlfn.SEQUENCE(LEN(G25)))) - 1)} -> CM | J25: =_xlfn.XLOOKUP(H25,'GK IFT SDM POSTCODES'!A:A,'GK IFT SDM POSTCODES'!B:B,"") -> Neil Stebbings | K25: GROW - Stella/SM +1 | L25: This guy is a prick. But got him to agree San Mig IPO Fosters in principal so this is mine. Sorry not sorry
A26: Greene King IFT | B26: Little Elms (Witham) | G26: CM8 2LX | H26: =_xlfn.TEXTBEFORE(G26," ") -> CM8 | I26: {=LEFT(G26, MIN(IF(ISNUMBER(--MID(G26, _xlfn.SEQUENCE(LEN(G26)), 1)), _xlfn.SEQUENCE(LEN(G26)))) - 1)} -> CM | J26: =_xlfn.XLOOKUP(H26,'GK IFT SDM POSTCODES'!A:A,'GK IFT SDM POSTCODES'!B:B,"") -> Neil Stebbings | K26: KEEP | L26: Worst pub I've ever been to. Take a stab vest. LL never in
A27: Greene King IFT | B27: Crittall Athletic & Social Club (Si | G27: CM8 3RQ | H27: =_xlfn.TEXTBEFORE(G27," ") -> CM8 | I27: {=LEFT(G27, MIN(IF(ISNUMBER(--MID(G27, _xlfn.SEQUENCE(LEN(G27)), 1)), _xlfn.SEQUENCE(LEN(G27)))) - 1)} -> CM | J27: =_xlfn.XLOOKUP(H27,'GK IFT SDM POSTCODES'!A:A,'GK IFT SDM POSTCODES'!B:B,"") -> Neil Stebbings | K27: GET | L27: Bud Light and Stella on here. Do pretty well but I would visit just to keep close
A28: Greene King L&T | B28: Western Arms | C28: Western Road | D28: Silver End | E28: Witham | F28: Essex | G28: CM8 3SD | H28: =_xlfn.TEXTBEFORE(G28," ") -> CM8 | I28: {=LEFT(G28, MIN(IF(ISNUMBER(--MID(G28, _xlfn.SEQUENCE(LEN(G28)), 1)), _xlfn.SEQUENCE(LEN(G28)))) - 1)} -> CM | J28: James Pearson | K28: GROW | L28: Jamie is LL and also has Rose Inn on my patch. Wsnts to turn this place into an american smokehouse but doesn’t want Bud or Bud Light? JP keen for us here to pick up with him
A29: Greene King IFT | B29: Stepfield Snooker Club (Witham) | G29: CM8 3TH | H29: =_xlfn.TEXTBEFORE(G29," ") -> CM8 | I29: {=LEFT(G29, MIN(IF(ISNUMBER(--MID(G29, _xlfn.SEQUENCE(LEN(G29)), 1)), _xlfn.SEQUENCE(LEN(G29)))) - 1)} -> CM | J29: =_xlfn.XLOOKUP(H29,'GK IFT SDM POSTCODES'!A:A,'GK IFT SDM POSTCODES'!B:B,"") -> Neil Stebbings | K29: KEEP | L29: Strong vols and on TNT deal. Keep close and you could get another line to tip them to the 2k mark
A30: Greene King IFT | B30: Old Ship (Maldon) | G30: CM9 4RX | H30: =_xlfn.TEXTBEFORE(G30," ") -> CM9 | I30: {=LEFT(G30, MIN(IF(ISNUMBER(--MID(G30, _xlfn.SEQUENCE(LEN(G30)), 1)), _xlfn.SEQUENCE(LEN(G30)))) - 1)} -> CM | J30: =_xlfn.XLOOKUP(H30,'GK IFT SDM POSTCODES'!A:A,'GK IFT SDM POSTCODES'!B:B,"") -> Neil Stebbings | K30: GROW - Stella/SM +1 | L30: Also own Fish on Quay. Don’t buy through GK anymore
A31: Greene King IFT | B31: Old Ship (Lockhill) | G31: CM9 4RX | H31: =_xlfn.TEXTBEFORE(G31," ") -> CM9 | I31: {=LEFT(G31, MIN(IF(ISNUMBER(--MID(G31, _xlfn.SEQUENCE(LEN(G31)), 1)), _xlfn.SEQUENCE(LEN(G31)))) - 1)} -> CM | J31: =_xlfn.XLOOKUP(H31,'GK IFT SDM POSTCODES'!A:A,'GK IFT SDM POSTCODES'!B:B,"") -> Neil Stebbings
A32: Stonegate | B32: Black Rabbit | C32: 188 High Street | E32: Maldon | F32: Essex | G32: CM9 5BX | H32: =_xlfn.TEXTBEFORE(G32," ") -> CM9 | I32: {=LEFT(G32, MIN(IF(ISNUMBER(--MID(G32, _xlfn.SEQUENCE(LEN(G32)), 1)), _xlfn.SEQUENCE(LEN(G32)))) - 1)} -> CM | J32: Kellie Newell | K32: GET | L32: MO that also has Rising Sun, CM2. Evan notorisouly difficult to get ahold. TNT want this and was on Modelo hitlist
A33: Greene King IFT | B33: Jolly Sailors (Maldon) | G33: CM9 5HP | H33: =_xlfn.TEXTBEFORE(G33," ") -> CM9 | I33: {=LEFT(G33, MIN(IF(ISNUMBER(--MID(G33, _xlfn.SEQUENCE(LEN(G33)), 1)), _xlfn.SEQUENCE(LEN(G33)))) - 1)} -> CM | J33: =_xlfn.XLOOKUP(H33,'GK IFT SDM POSTCODES'!A:A,'GK IFT SDM POSTCODES'!B:B,"") -> Neil Stebbings
A34: Greene King IFT | B34: Maldon & Tiptree FC (Maldon) | G34: CM9 5JQ | H34: =_xlfn.TEXTBEFORE(G34," ") -> CM9 | I34: {=LEFT(G34, MIN(IF(ISNUMBER(--MID(G34, _xlfn.SEQUENCE(LEN(G34)), 1)), _xlfn.SEQUENCE(LEN(G34)))) - 1)} -> CM | J34: =_xlfn.XLOOKUP(H34,'GK IFT SDM POSTCODES'!A:A,'GK IFT SDM POSTCODES'!B:B,"") -> Neil Stebbings | K34: GROW - Stella/SM +1
A35: Greene King IFT | B35: Maldon & District Cons Club (Maldon | G35: CM9 6AA | H35: =_xlfn.TEXTBEFORE(G35," ") -> CM9 | I35: {=LEFT(G35, MIN(IF(ISNUMBER(--MID(G35, _xlfn.SEQUENCE(LEN(G35)), 1)), _xlfn.SEQUENCE(LEN(G35)))) - 1)} -> CM | J35: =_xlfn.XLOOKUP(H35,'GK IFT SDM POSTCODES'!A:A,'GK IFT SDM POSTCODES'!B:B,"") -> Neil Stebbings | K35: GET | L35: Buy through CMBC but good opps here
A36: Greene King IFT | B36: White Horse (Mundon) | G36: CM9 6PB | H36: =_xlfn.TEXTBEFORE(G36," ") -> CM9 | I36: {=LEFT(G36, MIN(IF(ISNUMBER(--MID(G36, _xlfn.SEQUENCE(LEN(G36)), 1)), _xlfn.SEQUENCE(LEN(G36)))) - 1)} -> CM | J36: =_xlfn.XLOOKUP(H36,'GK IFT SDM POSTCODES'!A:A,'GK IFT SDM POSTCODES'!B:B,"") -> Neil Stebbings | K36: GET
A37: Punch | B37: Chequers | C37: Church Street | E37: Maldon | G37: CM9 8AS | H37: =_xlfn.TEXTBEFORE(G37," ") -> CM9 | I37: {=LEFT(G37, MIN(IF(ISNUMBER(--MID(G37, _xlfn.SEQUENCE(LEN(G37)), 1)), _xlfn.SEQUENCE(LEN(G37)))) - 1)} -> CM | J37: Mark Nield | K37: GET
A38: Greene King IFT | B38: Forrester Park (Maldon) | G38: CM9 8EA | H38: =_xlfn.TEXTBEFORE(G38," ") -> CM9 | I38: {=LEFT(G38, MIN(IF(ISNUMBER(--MID(G38, _xlfn.SEQUENCE(LEN(G38)), 1)), _xlfn.SEQUENCE(LEN(G38)))) - 1)} -> CM | J38: =_xlfn.XLOOKUP(H38,'GK IFT SDM POSTCODES'!A:A,'GK IFT SDM POSTCODES'!B:B,"") -> Neil Stebbings | K38: GROW - Stella/SM +1 | L38: Don’t bother
A39: Greene King IFT | B39: Forrester Park Golf Club (Maldon) | G39: CM9 8EA | H39: =_xlfn.TEXTBEFORE(G39," ") -> CM9 | I39: {=LEFT(G39, MIN(IF(ISNUMBER(--MID(G39, _xlfn.SEQUENCE(LEN(G39)), 1)), _xlfn.SEQUENCE(LEN(G39)))) - 1)} -> CM | J39: =_xlfn.XLOOKUP(H39,'GK IFT SDM POSTCODES'!A:A,'GK IFT SDM POSTCODES'!B:B,"") -> Neil Stebbings | K39: GROW - Stella/SM +1 | L39: Don’t bother
A40: Greene King IFT | B40: Five Lakes Essex (Maldon) | G40: CM9 8HX | H40: =_xlfn.TEXTBEFORE(G40," ") -> CM9 | I40: {=LEFT(G40, MIN(IF(ISNUMBER(--MID(G40, _xlfn.SEQUENCE(LEN(G40)), 1)), _xlfn.SEQUENCE(LEN(G40)))) - 1)} -> CM | J40: =_xlfn.XLOOKUP(H40,'GK IFT SDM POSTCODES'!A:A,'GK IFT SDM POSTCODES'!B:B,"") -> Neil Stebbings | K40: GROW | L40: Contracted with GK. Putts and Fras look after but good for exec check and build r'ships for next tender
A41: Greene King IFT | B41: Five Lakes (Maldon) | G41: CM9 8HX | H41: =_xlfn.TEXTBEFORE(G41," ") -> CM9 | I41: {=LEFT(G41, MIN(IF(ISNUMBER(--MID(G41, _xlfn.SEQUENCE(LEN(G41)), 1)), _xlfn.SEQUENCE(LEN(G41)))) - 1)} -> CM | J41: =_xlfn.XLOOKUP(H41,'GK IFT SDM POSTCODES'!A:A,'GK IFT SDM POSTCODES'!B:B,"") -> Neil Stebbings | K41: GROW | L41: Contracted with GK. Putts and Fras look after but good for exec check and build r'ships for next tender
A42: Punch | B42: Prince Of Wales | C42: 2 Prince Of Wales Road | E42: Maldon | G42: CM9 8PX | H42: =_xlfn.TEXTBEFORE(G42," ") -> CM9 | I42: {=LEFT(G42, MIN(IF(ISNUMBER(--MID(G42, _xlfn.SEQUENCE(LEN(G42)), 1)), _xlfn.SEQUENCE(LEN(G42)))) - 1)} -> CM | J42: Graham Roberts | K42: KEEP | L42: Good premium country site so decent opps for new Punch contract
A43: Greene King IFT | B43: Three Wise Monkeys (Colchester) | G43: CO1 1DN | H43: =_xlfn.TEXTBEFORE(G43," ") -> CO1 | I43: {=LEFT(G43, MIN(IF(ISNUMBER(--MID(G43, _xlfn.SEQUENCE(LEN(G43)), 1)), _xlfn.SEQUENCE(LEN(G43)))) - 1)} -> CO | J43: =_xlfn.XLOOKUP(H43,'GK IFT SDM POSTCODES'!A:A,'GK IFT SDM POSTCODES'!B:B,"") -> Nikki Hayter
A44: Greene King IFT | B44: Firstsite Ltd (Colchester) | G44: CO1 1JH | H44: =_xlfn.TEXTBEFORE(G44," ") -> CO1 | I44: {=LEFT(G44, MIN(IF(ISNUMBER(--MID(G44, _xlfn.SEQUENCE(LEN(G44)), 1)), _xlfn.SEQUENCE(LEN(G44)))) - 1)} -> CO | J44: =_xlfn.XLOOKUP(H44,'GK IFT SDM POSTCODES'!A:A,'GK IFT SDM POSTCODES'!B:B,"") -> Nikki Hayter
A45: Stonegate MNG | B45: Walkabout Colchester | C45: 29-39 Head Street | E45: Colchester | F45: Essex | G45: CO1 1NH | H45: =_xlfn.TEXTBEFORE(G45," ") -> CO1 | I45: {=LEFT(G45, MIN(IF(ISNUMBER(--MID(G45, _xlfn.SEQUENCE(LEN(G45)), 1)), _xlfn.SEQUENCE(LEN(G45)))) - 1)} -> CO | J45: Jenny Kuhn
A46: Greene King IFT | B46: Hudson (Colchester) | G46: CO1 1NX | H46: =_xlfn.TEXTBEFORE(G46," ") -> CO1 | I46: {=LEFT(G46, MIN(IF(ISNUMBER(--MID(G46, _xlfn.SEQUENCE(LEN(G46)), 1)), _xlfn.SEQUENCE(LEN(G46)))) - 1)} -> CO | J46: =_xlfn.XLOOKUP(H46,'GK IFT SDM POSTCODES'!A:A,'GK IFT SDM POSTCODES'!B:B,"") -> Nikki Hayter
A47: Stonegate MNG | B47: The Centurion Colchester | C47: 66 North Hill | E47: Colchester | F47: Essex | G47: CO1 1PX | H47: =_xlfn.TEXTBEFORE(G47," ") -> CO1 | I47: {=LEFT(G47, MIN(IF(ISNUMBER(--MID(G47, _xlfn.SEQUENCE(LEN(G47)), 1)), _xlfn.SEQUENCE(LEN(G47)))) - 1)} -> CO | J47: Jenny Kuhn
A48: Greene King IFT | B48: Twisters Cafe Bar (Colchester) | G48: CO1 1PY | H48: =_xlfn.TEXTBEFORE(G48," ") -> CO1 | I48: {=LEFT(G48, MIN(IF(ISNUMBER(--MID(G48, _xlfn.SEQUENCE(LEN(G48)), 1)), _xlfn.SEQUENCE(LEN(G48)))) - 1)} -> CO | J48: =_xlfn.XLOOKUP(H48,'GK IFT SDM POSTCODES'!A:A,'GK IFT SDM POSTCODES'!B:B,"") -> Nikki Hayter
A49: Greene King IFT | B49: Pavilion (Colchester) | G49: CO1 1QX | H49: =_xlfn.TEXTBEFORE(G49," ") -> CO1 | I49: {=LEFT(G49, MIN(IF(ISNUMBER(--MID(G49, _xlfn.SEQUENCE(LEN(G49)), 1)), _xlfn.SEQUENCE(LEN(G49)))) - 1)} -> CO | J49: =_xlfn.XLOOKUP(H49,'GK IFT SDM POSTCODES'!A:A,'GK IFT SDM POSTCODES'!B:B,"") -> Nikki Hayter
A50: Stonegate MNG | B50: Slug And Lettuce Colchester | C50: 111 High Street | E50: Colchester | F50: Essex | G50: CO1 1TB | H50: =_xlfn.TEXTBEFORE(G50," ") -> CO1 | I50: {=LEFT(G50, MIN(IF(ISNUMBER(--MID(G50, _xlfn.SEQUENCE(LEN(G50)), 1)), _xlfn.SEQUENCE(LEN(G50)))) - 1)} -> CO | J50: Kristopher Reed
A51: Admiral | B51: Foresters Arms, Colchester | C51: Castle Road, | E51: Colchester | G51: CO1 1UW | H51: =_xlfn.TEXTBEFORE(G51," ") -> CO1 | I51: {=LEFT(G51, MIN(IF(ISNUMBER(--MID(G51, _xlfn.SEQUENCE(LEN(G51)), 1)), _xlfn.SEQUENCE(LEN(G51)))) - 1)} -> CO | J51: James McIver
A52: Greene King IFT | B52: Colchester & East Essex Cricket Clu | G52: CO1 1XN | H52: =_xlfn.TEXTBEFORE(G52," ") -> CO1 | I52: {=LEFT(G52, MIN(IF(ISNUMBER(--MID(G52, _xlfn.SEQUENCE(LEN(G52)), 1)), _xlfn.SEQUENCE(LEN(G52)))) - 1)} -> CO | J52: =_xlfn.XLOOKUP(H52,'GK IFT SDM POSTCODES'!A:A,'GK IFT SDM POSTCODES'!B:B,"") -> Nikki Hayter
A53: Greene King IFT | B53: Royal Mortar (Colchester) | G53: CO1 2AS | H53: =_xlfn.TEXTBEFORE(G53," ") -> CO1 | I53: {=LEFT(G53, MIN(IF(ISNUMBER(--MID(G53, _xlfn.SEQUENCE(LEN(G53)), 1)), _xlfn.SEQUENCE(LEN(G53)))) - 1)} -> CO | J53: =_xlfn.XLOOKUP(H53,'GK IFT SDM POSTCODES'!A:A,'GK IFT SDM POSTCODES'!B:B,"") -> Nikki Hayter
A54: Greene King MNG | B54: Artilleryman | C54: 54-56 Artillery Street | D54: Colchester | F54: Essex | G54: CO1 2JQ | H54: =_xlfn.TEXTBEFORE(G54," ") -> CO1 | I54: {=LEFT(G54, MIN(IF(ISNUMBER(--MID(G54, _xlfn.SEQUENCE(LEN(G54)), 1)), _xlfn.SEQUENCE(LEN(G54)))) - 1)} -> CO | J54: Hannah Mills
A55: Greene King L&T | B55: Goat & Boot | C55: 70 East Hill | D55: Colchester | F55: Essex | G55: CO1 2QW | H55: =_xlfn.TEXTBEFORE(G55," ") -> CO1 | I55: {=LEFT(G55, MIN(IF(ISNUMBER(--MID(G55, _xlfn.SEQUENCE(LEN(G55)), 1)), _xlfn.SEQUENCE(LEN(G55)))) - 1)} -> CO | J55: James Pearson
A56: Greene King IFT | B56: Curve (Colchester) | G56: CO1 2QW | H56: =_xlfn.TEXTBEFORE(G56," ") -> CO1 | I56: {=LEFT(G56, MIN(IF(ISNUMBER(--MID(G56, _xlfn.SEQUENCE(LEN(G56)), 1)), _xlfn.SEQUENCE(LEN(G56)))) - 1)} -> CO | J56: =_xlfn.XLOOKUP(H56,'GK IFT SDM POSTCODES'!A:A,'GK IFT SDM POSTCODES'!B:B,"") -> Nikki Hayter
A57: Greene King IFT | B57: Old Siege House Bar (Colchester) | G57: CO1 2TS | H57: =_xlfn.TEXTBEFORE(G57," ") -> CO1 | I57: {=LEFT(G57, MIN(IF(ISNUMBER(--MID(G57, _xlfn.SEQUENCE(LEN(G57)), 1)), _xlfn.SEQUENCE(LEN(G57)))) - 1)} -> CO | J57: =_xlfn.XLOOKUP(H57,'GK IFT SDM POSTCODES'!A:A,'GK IFT SDM POSTCODES'!B:B,"") -> Nikki Hayter
A58: Greene King L&T | B58: Crown | C58: High Street | D58: Acton | E58: Sudbury | F58: Suffolk | G58: CO10 0AT | H58: =_xlfn.TEXTBEFORE(G58," ") -> CO10 | I58: {=LEFT(G58, MIN(IF(ISNUMBER(--MID(G58, _xlfn.SEQUENCE(LEN(G58)), 1)), _xlfn.SEQUENCE(LEN(G58)))) - 1)} -> CO | J58: Samantha Wortley
A59: Greene King L&T | B59: Kings Head | C59: 115 Bures Road | D59: Great Cornard | E59: Sudbury | F59: Suffolk | G59: CO10 0JE | H59: =_xlfn.TEXTBEFORE(G59," ") -> CO10 | I59: {=LEFT(G59, MIN(IF(ISNUMBER(--MID(G59, _xlfn.SEQUENCE(LEN(G59)), 1)), _xlfn.SEQUENCE(LEN(G59)))) - 1)} -> CO | J59: Samantha Wortley
A60: Greene King IFT | B60: Saracens Head (Newton) | G60: CO10 0QJ | H60: =_xlfn.TEXTBEFORE(G60," ") -> CO10 | I60: {=LEFT(G60, MIN(IF(ISNUMBER(--MID(G60, _xlfn.SEQUENCE(LEN(G60)), 1)), _xlfn.SEQUENCE(LEN(G60)))) - 1)} -> CO | J60: =_xlfn.XLOOKUP(H60,'GK IFT SDM POSTCODES'!A:A,'GK IFT SDM POSTCODES'!B:B,"") -> Kate Rayson
A61: Greene King IFT | B61: White Horse (Gt Waldingfield) | G61: CO10 0RW | H61: =_xlfn.TEXTBEFORE(G61," ") -> CO10 | I61: {=LEFT(G61, MIN(IF(ISNUMBER(--MID(G61, _xlfn.SEQUENCE(LEN(G61)), 1)), _xlfn.SEQUENCE(LEN(G61)))) - 1)} -> CO | J61: =_xlfn.XLOOKUP(H61,'GK IFT SDM POSTCODES'!A:A,'GK IFT SDM POSTCODES'!B:B,"") -> Kate Rayson
A62: Greene King IFT | B62: Northcroft Social Club (Sudbury) | G62: CO10 1HN | H62: =_xlfn.TEXTBEFORE(G62," ") -> CO10 | I62: {=LEFT(G62, MIN(IF(ISNUMBER(--MID(G62, _xlfn.SEQUENCE(LEN(G62)), 1)), _xlfn.SEQUENCE(LEN(G62)))) - 1)} -> CO | J62: =_xlfn.XLOOKUP(H62,'GK IFT SDM POSTCODES'!A:A,'GK IFT SDM POSTCODES'!B:B,"") -> Kate Rayson
A63: Greene King IFT | B63: Masonic Hall Manager (Sudbury) | G63: CO10 1NA | H63: =_xlfn.TEXTBEFORE(G63," ") -> CO10 | I63: {=LEFT(G63, MIN(IF(ISNUMBER(--MID(G63, _xlfn.SEQUENCE(LEN(G63)), 1)), _xlfn.SEQUENCE(LEN(G63)))) - 1)} -> CO | J63: =_xlfn.XLOOKUP(H63,'GK IFT SDM POSTCODES'!A:A,'GK IFT SDM POSTCODES'!B:B,"") -> Kate Rayson
A64: Greene King IFT | B64: Sudbury Snooker Club (Sudbury) | G64: CO10 1RE | H64: =_xlfn.TEXTBEFORE(G64," ") -> CO10 | I64: {=LEFT(G64, MIN(IF(ISNUMBER(--MID(G64, _xlfn.SEQUENCE(LEN(G64)), 1)), _xlfn.SEQUENCE(LEN(G64)))) - 1)} -> CO | J64: =_xlfn.XLOOKUP(H64,'GK IFT SDM POSTCODES'!A:A,'GK IFT SDM POSTCODES'!B:B,"") -> Kate Rayson
A65: Greene King IFT | B65: Sudbury Snooker Club and Function R | G65: CO10 1RE | H65: =_xlfn.TEXTBEFORE(G65," ") -> CO10 | I65: {=LEFT(G65, MIN(IF(ISNUMBER(--MID(G65, _xlfn.SEQUENCE(LEN(G65)), 1)), _xlfn.SEQUENCE(LEN(G65)))) - 1)} -> CO | J65: =_xlfn.XLOOKUP(H65,'GK IFT SDM POSTCODES'!A:A,'GK IFT SDM POSTCODES'!B:B,"") -> Kate Rayson
A66: Admiral | B66: North Street Tavern, Sudbury | C66: 66 North Street, | E66: Sudbury | G66: CO10 1RE | H66: =_xlfn.TEXTBEFORE(G66," ") -> CO10 | I66: {=LEFT(G66, MIN(IF(ISNUMBER(--MID(G66, _xlfn.SEQUENCE(LEN(G66)), 1)), _xlfn.SEQUENCE(LEN(G66)))) - 1)} -> CO | J66: Nicky Bellingham
A67: Greene King L&T | B67: White Horse | C67: North Street | D67: Sudbury | F67: Suffolk | G67: CO10 1RF | H67: =_xlfn.TEXTBEFORE(G67," ") -> CO10 | I67: {=LEFT(G67, MIN(IF(ISNUMBER(--MID(G67, _xlfn.SEQUENCE(LEN(G67)), 1)), _xlfn.SEQUENCE(LEN(G67)))) - 1)} -> CO | J67: Samantha Wortley
A68: Admiral | B68: Angel, Sudbury | C68: 43 Friars Street, | E68: Sudbury | G68: CO10 2AG | H68: =_xlfn.TEXTBEFORE(G68," ") -> CO10 | I68: {=LEFT(G68, MIN(IF(ISNUMBER(--MID(G68, _xlfn.SEQUENCE(LEN(G68)), 1)), _xlfn.SEQUENCE(LEN(G68)))) - 1)} -> CO | J68: James McIver
A69: Greene King L&T | B69: Lady Elizabeth | C69: Market Hill | D69: Sudbury | F69: Suffolk | G69: CO10 2EA | H69: =_xlfn.TEXTBEFORE(G69," ") -> CO10 | I69: {=LEFT(G69, MIN(IF(ISNUMBER(--MID(G69, _xlfn.SEQUENCE(LEN(G69)), 1)), _xlfn.SEQUENCE(LEN(G69)))) - 1)} -> CO | J69: Samantha Wortley
A70: Greene King IFT | B70: Comfortable Cow (Sudbury) | G70: CO10 2EB | H70: =_xlfn.TEXTBEFORE(G70," ") -> CO10 | I70: {=LEFT(G70, MIN(IF(ISNUMBER(--MID(G70, _xlfn.SEQUENCE(LEN(G70)), 1)), _xlfn.SEQUENCE(LEN(G70)))) - 1)} -> CO | J70: =_xlfn.XLOOKUP(H70,'GK IFT SDM POSTCODES'!A:A,'GK IFT SDM POSTCODES'!B:B,"") -> Kate Rayson
A71: Greene King IFT | B71: Sporty Cow (Sudbury) | G71: CO10 2EB | H71: =_xlfn.TEXTBEFORE(G71," ") -> CO10 | I71: {=LEFT(G71, MIN(IF(ISNUMBER(--MID(G71, _xlfn.SEQUENCE(LEN(G71)), 1)), _xlfn.SEQUENCE(LEN(G71)))) - 1)} -> CO | J71: =_xlfn.XLOOKUP(H71,'GK IFT SDM POSTCODES'!A:A,'GK IFT SDM POSTCODES'!B:B,"") -> Kate Rayson
A72: Stonegate | B72: Weavers Tap Sudbury | C72: Queensbury House East Street | E72: Sudbury | F72: Suffolk | G72: CO10 2HX | H72: =_xlfn.TEXTBEFORE(G72," ") -> CO10 | I72: {=LEFT(G72, MIN(IF(ISNUMBER(--MID(G72, _xlfn.SEQUENCE(LEN(G72)), 1)), _xlfn.SEQUENCE(LEN(G72)))) - 1)} -> CO | J72: Kellie Newell
A73: Greene King MNG | B73: Maldon Grey | C73: Cats Lane | D73: Sudbury | F73: Suffolk | G73: CO10 2RZ | H73: =_xlfn.TEXTBEFORE(G73," ") -> CO10 | I73: {=LEFT(G73, MIN(IF(ISNUMBER(--MID(G73, _xlfn.SEQUENCE(LEN(G73)), 1)), _xlfn.SEQUENCE(LEN(G73)))) - 1)} -> CO | J73: Hannah Mills
A74: Greene King IFT | B74: Institute Club (Sudbury) | G74: CO10 2SP | H74: =_xlfn.TEXTBEFORE(G74," ") -> CO10 | I74: {=LEFT(G74, MIN(IF(ISNUMBER(--MID(G74, _xlfn.SEQUENCE(LEN(G74)), 1)), _xlfn.SEQUENCE(LEN(G74)))) - 1)} -> CO | J74: =_xlfn.XLOOKUP(H74,'GK IFT SDM POSTCODES'!A:A,'GK IFT SDM POSTCODES'!B:B,"") -> Kate Rayson
A75: Admiral | B75: Horse & Groom, Sudbury | C75: 35 East Street, | E75: Sudbury | G75: CO10 2TU | H75: =_xlfn.TEXTBEFORE(G75," ") -> CO10 | I75: {=LEFT(G75, MIN(IF(ISNUMBER(--MID(G75, _xlfn.SEQUENCE(LEN(G75)), 1)), _xlfn.SEQUENCE(LEN(G75)))) - 1)} -> CO | J75: James McIver
A76: Greene King IFT | B76: White Hart (Boxford) | G76: CO10 5DX | H76: =_xlfn.TEXTBEFORE(G76," ") -> CO10 | I76: {=LEFT(G76, MIN(IF(ISNUMBER(--MID(G76, _xlfn.SEQUENCE(LEN(G76)), 1)), _xlfn.SEQUENCE(LEN(G76)))) - 1)} -> CO | J76: =_xlfn.XLOOKUP(H76,'GK IFT SDM POSTCODES'!A:A,'GK IFT SDM POSTCODES'!B:B,"") -> Kate Rayson
A77: Greene King IFT | B77: Red Lion (Belchamp Otten) | G77: CO10 7BQ | H77: =_xlfn.TEXTBEFORE(G77," ") -> CO10 | I77: {=LEFT(G77, MIN(IF(ISNUMBER(--MID(G77, _xlfn.SEQUENCE(LEN(G77)), 1)), _xlfn.SEQUENCE(LEN(G77)))) - 1)} -> CO | J77: =_xlfn.XLOOKUP(H77,'GK IFT SDM POSTCODES'!A:A,'GK IFT SDM POSTCODES'!B:B,"") -> Kate Rayson
A78: Greene King IFT | B78: AFC Sudbury (Sudbury) | G78: CO10 7HN | H78: =_xlfn.TEXTBEFORE(G78," ") -> CO10 | I78: {=LEFT(G78, MIN(IF(ISNUMBER(--MID(G78, _xlfn.SEQUENCE(LEN(G78)), 1)), _xlfn.SEQUENCE(LEN(G78)))) - 1)} -> CO | J78: =_xlfn.XLOOKUP(H78,'GK IFT SDM POSTCODES'!A:A,'GK IFT SDM POSTCODES'!B:B,"") -> Kate Rayson
A79: Greene King IFT | B79: Bridge Project (Sudbury) | G79: CO10 7HN | H79: =_xlfn.TEXTBEFORE(G79," ") -> CO10 | I79: {=LEFT(G79, MIN(IF(ISNUMBER(--MID(G79, _xlfn.SEQUENCE(LEN(G79)), 1)), _xlfn.SEQUENCE(LEN(G79)))) - 1)} -> CO | J79: =_xlfn.XLOOKUP(H79,'GK IFT SDM POSTCODES'!A:A,'GK IFT SDM POSTCODES'!B:B,"") -> Kate Rayson
A80: Greene King IFT | B80: Glemsford Social Club | G80: CO10 7RP | H80: =_xlfn.TEXTBEFORE(G80," ") -> CO10 | I80: {=LEFT(G80, MIN(IF(ISNUMBER(--MID(G80, _xlfn.SEQUENCE(LEN(G80)), 1)), _xlfn.SEQUENCE(LEN(G80)))) - 1)} -> CO | J80: =_xlfn.XLOOKUP(H80,'GK IFT SDM POSTCODES'!A:A,'GK IFT SDM POSTCODES'!B:B,"") -> Kate Rayson
A81: Admiral | B81: Angel, Glemsford | C81: Egremont Street, | E81: Glemsford | G81: CO10 7SA | H81: =_xlfn.TEXTBEFORE(G81," ") -> CO10 | I81: {=LEFT(G81, MIN(IF(ISNUMBER(--MID(G81, _xlfn.SEQUENCE(LEN(G81)), 1)), _xlfn.SEQUENCE(LEN(G81)))) - 1)} -> CO | J81: James McIver
A82: Greene King IFT | B82: Bull Inn (Cavendish) | G82: CO10 8AX | H82: =_xlfn.TEXTBEFORE(G82," ") -> CO10 | I82: {=LEFT(G82, MIN(IF(ISNUMBER(--MID(G82, _xlfn.SEQUENCE(LEN(G82)), 1)), _xlfn.SEQUENCE(LEN(G82)))) - 1)} -> CO | J82: =_xlfn.XLOOKUP(H82,'GK IFT SDM POSTCODES'!A:A,'GK IFT SDM POSTCODES'!B:B,"") -> Kate Rayson
A83: Greene King IFT | B83: Five Bells (Cavendish) | G83: CO10 8BA | H83: =_xlfn.TEXTBEFORE(G83," ") -> CO10 | I83: {=LEFT(G83, MIN(IF(ISNUMBER(--MID(G83, _xlfn.SEQUENCE(LEN(G83)), 1)), _xlfn.SEQUENCE(LEN(G83)))) - 1)} -> CO | J83: =_xlfn.XLOOKUP(H83,'GK IFT SDM POSTCODES'!A:A,'GK IFT SDM POSTCODES'!B:B,"") -> Kate Rayson
A84: Greene King IFT | B84: George (Cavendish) | G84: CO10 8BA | H84: =_xlfn.TEXTBEFORE(G84," ") -> CO10 | I84: {=LEFT(G84, MIN(IF(ISNUMBER(--MID(G84, _xlfn.SEQUENCE(LEN(G84)), 1)), _xlfn.SEQUENCE(LEN(G84)))) - 1)} -> CO | J84: =_xlfn.XLOOKUP(H84,'GK IFT SDM POSTCODES'!A:A,'GK IFT SDM POSTCODES'!B:B,"") -> Kate Rayson
A85: Admiral | B85: Lion, Sudbury | C85: The Street, Stoke-By-Clare | E85: Sudbury | G85: CO10 8HP | H85: =_xlfn.TEXTBEFORE(G85," ") -> CO10 | I85: {=LEFT(G85, MIN(IF(ISNUMBER(--MID(G85, _xlfn.SEQUENCE(LEN(G85)), 1)), _xlfn.SEQUENCE(LEN(G85)))) - 1)} -> CO | J85: James McIver
A86: Admiral | B86: Swan, Clare | C86: 4 High Street, Clare | E86: Sudbury | G86: CO10 8NY | H86: =_xlfn.TEXTBEFORE(G86," ") -> CO10 | I86: {=LEFT(G86, MIN(IF(ISNUMBER(--MID(G86, _xlfn.SEQUENCE(LEN(G86)), 1)), _xlfn.SEQUENCE(LEN(G86)))) - 1)} -> CO | J86: James McIver
A87: Greene King L&T | B87: Hare | C87: High Street | D87: Long Melford | E87: Sudbury | F87: Suffolk | G87: CO10 9DF | H87: =_xlfn.TEXTBEFORE(G87," ") -> CO10 | I87: {=LEFT(G87, MIN(IF(ISNUMBER(--MID(G87, _xlfn.SEQUENCE(LEN(G87)), 1)), _xlfn.SEQUENCE(LEN(G87)))) - 1)} -> CO | J87: Samantha Wortley
A88: Greene King L&T | B88: George & Dragon | C88: Hall Street | D88: Long Melford | E88: Sudbury | F88: Suffolk | G88: CO10 9JA | H88: =_xlfn.TEXTBEFORE(G88," ") -> CO10 | I88: {=LEFT(G88, MIN(IF(ISNUMBER(--MID(G88, _xlfn.SEQUENCE(LEN(G88)), 1)), _xlfn.SEQUENCE(LEN(G88)))) - 1)} -> CO | J88: Samantha Wortley
A89: Greene King IFT | B89: George & Dragon (Long Melford) | G89: CO10 9JA | H89: =_xlfn.TEXTBEFORE(G89," ") -> CO10 | I89: {=LEFT(G89, MIN(IF(ISNUMBER(--MID(G89, _xlfn.SEQUENCE(LEN(G89)), 1)), _xlfn.SEQUENCE(LEN(G89)))) - 1)} -> CO | J89: =_xlfn.XLOOKUP(H89,'GK IFT SDM POSTCODES'!A:A,'GK IFT SDM POSTCODES'!B:B,"") -> Kate Rayson
A90: Greene King IFT | B90: Crown Inn Hotel (Long Melford) | G90: CO10 9JL | H90: =_xlfn.TEXTBEFORE(G90," ") -> CO10 | I90: {=LEFT(G90, MIN(IF(ISNUMBER(--MID(G90, _xlfn.SEQUENCE(LEN(G90)), 1)), _xlfn.SEQUENCE(LEN(G90)))) - 1)} -> CO | J90: =_xlfn.XLOOKUP(H90,'GK IFT SDM POSTCODES'!A:A,'GK IFT SDM POSTCODES'!B:B,"") -> Kate Rayson
A91: Greene King L&T | B91: Swan | C91: Hall Street | D91: Long Melford | E91: Sudbury | F91: Suffolk | G91: CO10 9JQ | H91: =_xlfn.TEXTBEFORE(G91," ") -> CO10 | I91: {=LEFT(G91, MIN(IF(ISNUMBER(--MID(G91, _xlfn.SEQUENCE(LEN(G91)), 1)), _xlfn.SEQUENCE(LEN(G91)))) - 1)} -> CO | J91: Samantha Wortley
A92: Greene King IFT | B92: RBLC (Lavenham) | G92: CO10 9PT | H92: =_xlfn.TEXTBEFORE(G92," ") -> CO10 | I92: {=LEFT(G92, MIN(IF(ISNUMBER(--MID(G92, _xlfn.SEQUENCE(LEN(G92)), 1)), _xlfn.SEQUENCE(LEN(G92)))) - 1)} -> CO | J92: =_xlfn.XLOOKUP(H92,'GK IFT SDM POSTCODES'!A:A,'GK IFT SDM POSTCODES'!B:B,"") -> Kate Rayson
A93: Greene King L&T | B93: Greyhound | C93: 97 High Street | D93: Lavenham | E93: Sudbury | F93: Suffolk | G93: CO10 9PZ | H93: =_xlfn.TEXTBEFORE(G93," ") -> CO10 | I93: {=LEFT(G93, MIN(IF(ISNUMBER(--MID(G93, _xlfn.SEQUENCE(LEN(G93)), 1)), _xlfn.SEQUENCE(LEN(G93)))) - 1)} -> CO | J93: Samantha Wortley
A94: Greene King IFT | B94: Angel Hotel (Lavenham) | G94: CO10 9QZ | H94: =_xlfn.TEXTBEFORE(G94," ") -> CO10 | I94: {=LEFT(G94, MIN(IF(ISNUMBER(--MID(G94, _xlfn.SEQUENCE(LEN(G94)), 1)), _xlfn.SEQUENCE(LEN(G94)))) - 1)} -> CO | J94: =_xlfn.XLOOKUP(H94,'GK IFT SDM POSTCODES'!A:A,'GK IFT SDM POSTCODES'!B:B,"") -> Kate Rayson
A95: Greene King IFT | B95: Number Ten Wine Bar (Lavenham) | G95: CO10 9RA | H95: =_xlfn.TEXTBEFORE(G95," ") -> CO10 | I95: {=LEFT(G95, MIN(IF(ISNUMBER(--MID(G95, _xlfn.SEQUENCE(LEN(G95)), 1)), _xlfn.SEQUENCE(LEN(G95)))) - 1)} -> CO | J95: =_xlfn.XLOOKUP(H95,'GK IFT SDM POSTCODES'!A:A,'GK IFT SDM POSTCODES'!B:B,"") -> Kate Rayson
A96: Stonegate | B96: Cock Horse Lavenham | C96: Church Street Lavenham | E96: Sudbury | F96: Suffolk | G96: CO10 9SA | H96: =_xlfn.TEXTBEFORE(G96," ") -> CO10 | I96: {=LEFT(G96, MIN(IF(ISNUMBER(--MID(G96, _xlfn.SEQUENCE(LEN(G96)), 1)), _xlfn.SEQUENCE(LEN(G96)))) - 1)} -> CO | J96: Kellie Newell
A97: Greene King L&T | B97: Crown | C97: 51-53 High Street | D97: Manningtree | E97: Colchester | F97: Essex | G97: CO11 1AH | H97: =_xlfn.TEXTBEFORE(G97," ") -> CO11 | I97: {=LEFT(G97, MIN(IF(ISNUMBER(--MID(G97, _xlfn.SEQUENCE(LEN(G97)), 1)), _xlfn.SEQUENCE(LEN(G97)))) - 1)} -> CO | J97: James Pearson
A98: Punch | B98: Skinners | C98: Station Road | E98: Manningtree | G98: CO11 1DX | H98: =_xlfn.TEXTBEFORE(G98," ") -> CO11 | I98: {=LEFT(G98, MIN(IF(ISNUMBER(--MID(G98, _xlfn.SEQUENCE(LEN(G98)), 1)), _xlfn.SEQUENCE(LEN(G98)))) - 1)} -> CO | J98: Jason Harris
A99: Greene King IFT | B99: Mistley Cricket Club (Mistley) | G99: CO11 1ER | H99: =_xlfn.TEXTBEFORE(G99," ") -> CO11 | I99: {=LEFT(G99, MIN(IF(ISNUMBER(--MID(G99, _xlfn.SEQUENCE(LEN(G99)), 1)), _xlfn.SEQUENCE(LEN(G99)))) - 1)} -> CO | J99: =_xlfn.XLOOKUP(H99,'GK IFT SDM POSTCODES'!A:A,'GK IFT SDM POSTCODES'!B:B,"") -> Nikki Hayter
A100: Greene King IFT | B100: Crown (Brantham) | G100: CO11 1RE | H100: =_xlfn.TEXTBEFORE(G100," ") -> CO11 | I100: {=LEFT(G100, MIN(IF(ISNUMBER(--MID(G100, _xlfn.SEQUENCE(LEN(G100)), 1)), _xlfn.SEQUENCE(LEN(G100)))) - 1)} -> CO | J100: =_xlfn.XLOOKUP(H100,'GK IFT SDM POSTCODES'!A:A,'GK IFT SDM POSTCODES'!B:B,"") -> Nikki Hayter
...

Sheet GK IFT SDM POSTCODES
A1: Postcode | B1: SDM | C1: SDM Code | D1: Email Address | E1: RSM | F1: RSM Email Address | G1: Head of Sales | H1: Local Authority | I1: County
A2: AB10 | B2: Stevie Knox | C2: 708 | D2: steve.knox@belhaven.co.uk | E2: Graham Baird | F2: graham.baird@belhaven.co.uk | G2: Graham Baird | H2: Aberdeen City | I2: Aberdeenshire
A3: AB11 | B3: Stevie Knox | C3: 708 | D3: steve.knox@belhaven.co.uk | E3: Graham Baird | F3: graham.baird@belhaven.co.uk | G3: Graham Baird | H3: Aberdeen City | I3: Aberdeenshire
A4: AB12 | B4: Stevie Knox | C4: 708 | D4: steve.knox@belhaven.co.uk | E4: Graham Baird | F4: graham.baird@belhaven.co.uk | G4: Graham Baird | H4: Aberdeen City | I4: Aberdeenshire
A5: AB13 | B5: Stevie Knox | C5: 708 | D5: steve.knox@belhaven.co.uk | E5: Graham Baird | F5: graham.baird@belhaven.co.uk | G5: Graham Baird | H5: Scotland | I5: Scotland
A6: AB14 | B6: Stevie Knox | C6: 708 | D6: steve.knox@belhaven.co.uk | E6: Graham Baird | F6: graham.baird@belhaven.co.uk | G6: Graham Baird | H6: Aberdeen City | I6: Aberdeenshire
A7: AB15 | B7: Stevie Knox | C7: 708 | D7: steve.knox@belhaven.co.uk | E7: Graham Baird | F7: graham.baird@belhaven.co.uk | G7: Graham Baird | H7: Aberdeen City | I7: Aberdeenshire
A8: AB16 | B8: Stevie Knox | C8: 708 | D8: steve.knox@belhaven.co.uk | E8: Graham Baird | F8: graham.baird@belhaven.co.uk | G8: Graham Baird | H8: Aberdeen City | I8: Aberdeenshire
A9: AB21 | B9: Stevie Knox | C9: 708 | D9: steve.knox@belhaven.co.uk | E9: Graham Baird | F9: graham.baird@belhaven.co.uk | G9: Graham Baird | H9: Aberdeen City | I9: Aberdeenshire
A10: AB22 | B10: Stevie Knox | C10: 708 | D10: steve.knox@belhaven.co.uk | E10: Graham Baird | F10: graham.baird@belhaven.co.uk | G10: Graham Baird | H10: Aberdeen City | I10: Aberdeenshire
A11: AB23 | B11: Stevie Knox | C11: 708 | D11: steve.knox@belhaven.co.uk | E11: Graham Baird | F11: graham.baird@belhaven.co.uk | G11: Graham Baird | H11: Aberdeen City | I11: Aberdeenshire
A12: AB24 | B12: Stevie Knox | C12: 708 | D12: steve.knox@belhaven.co.uk | E12: Graham Baird | F12: graham.baird@belhaven.co.uk | G12: Graham Baird | H12: Aberdeen City | I12: Aberdeenshire
A13: AB25 | B13: Stevie Knox | C13: 708 | D13: steve.knox@belhaven.co.uk | E13: Graham Baird | F13: graham.baird@belhaven.co.uk | G13: Graham Baird | H13: Aberdeen City | I13: Aberdeenshire
... A288: BS9 | B288: Steve Ikin | C288: 227 | D288: steveikin@greeneking.co.uk | E288: Alan Dawson | F288: AlanDawson@greeneking.co.uk | G288: Scott Russell | H288: Bristol, City of | I288: Bristol
A289: BT1 | B289: Out of area | C289: OOA | E289: Out of Area | F289: Out of Area | G289: Out of Area | H289: Unknown | I289: Unknown
A290: BT10 | B290: Out of area | C290: OOA | E290: Out of Area | F290: Out of Area | G290: Out of Area | H290: Unknown | I290: Unknown
A291: BT11 | B291: Out of area | C291: OOA | E291: Out of Area | F291: Out of Area | G291: Out of Area | H291: Unknown | I291: Unknown
A292: BT12 | B292: Out of area | C292: OOA | E292: Out of Area | F292: Out of Area | G292: Out of Area | H292: Unknown | I292: Unknown
A293: BT13 | B293: Out of area | C293: OOA | E293: Out of Area | F293: Out of Area | G293: Out of Area | H293: Unknown | I293: Unknown
A294: BT14 | B294: Out of area | C294: OOA | E294: Out of Area | F294: Out of Area | G294: Out of Area | H294: Unknown | I294: Unknown
A295: BT15 | B295: Out of area | C295: OOA | E295: Out of Area | F295: Out of Area | G295: Out of Area | H295: Unknown | I295: Unknown
A296: BT16 | B296: Out of area | C296: OOA | E296: Out of Area | F296: Out of Area | G296: Out of Area | H296: Unknown | I296: Unknown
A297: BT17 | B297: Out of area | C297: OOA | E297: Out of Area | F297: Out of Area | G297: Out of Area | H297: Unknown | I297: Unknown
A298: BT18 | B298: Out of area | C298: OOA | E298: Out of Area | F298: Out of Area | G298: Out of Area | H298: Unknown | I298: Unknown
A299: BT19 | B299: Out of area | C299: OOA | E299: Out of Area | F299: Out of Area | G299: Out of Area | H299: Unknown | I299: Unknown
A300: BT2 | B300: Out of area | C300: OOA | E300: Out of Area | F300: Out of Area | G300: Out of Area | H300: Unknown | I300: Unknown
... A368: BT94 | B368: Out of area | C368: OOA | E368: Out of Area | F368: Out of Area | G368: Out of Area | H368: Unknown | I368: Unknown
A369: CA1 | B369: Roy Knox | C369: 709 | D369: royknox@greeneking.co.uk | E369: Kevan Makin | F369: kevan.makin@belhaven.co.uk | G369: Graham Baird | H369: Carlisle | I369: Cumbria
A370: CA10 | B370: Roy Knox | C370: 709 | D370: royknox@greeneking.co.uk | E370: Kevan Makin | F370: kevan.makin@belhaven.co.uk | G370: Graham Baird | H370: Scotland | I370: Scotland
A371: CA11 | B371: Roy Knox | C371: 709 | D371: royknox@greeneking.co.uk | E371: Kevan Makin | F371: kevan.makin@belhaven.co.uk | G371: Graham Baird | H371: Eden | I371: Cumbria
A372: CA12 | B372: Roy Knox | C372: 709 | D372: royknox@greeneking.co.uk | E372: Kevan Makin | F372: kevan.makin@belhaven.co.uk | G372: Graham Baird | H372: Allerdale | I372: Cumbria
A373: CA13 | B373: Roy Knox | C373: 709 | D373: royknox@greeneking.co.uk | E373: Kevan Makin | F373: kevan.makin@belhaven.co.uk | G373: Graham Baird | H373: Allerdale | I373: Cumbria
A374: CA14 | B374: Roy Knox | C374: 709 | D374: royknox@greeneking.co.uk | E374: Kevan Makin | F374: kevan.makin@belhaven.co.uk | G374: Graham Baird | H374: Scotland | I374: Scotland
A375: CA15 | B375: Roy Knox | C375: 709 | D375: royknox@greeneking.co.uk | E375: Kevan Makin | F375: kevan.makin@belhaven.co.uk | G375: Graham Baird | H375: Allerdale | I375: Cumbria
A376: CA16 | B376: Roy Knox | C376: 709 | D376: royknox@greeneking.co.uk | E376: Kevan Makin | F376: kevan.makin@belhaven.co.uk | G376: Graham Baird | H376: Eden | I376: Cumbria
A377: CA17 | B377: Roy Knox | C377: 709 | D377: royknox@greeneking.co.uk | E377: Kevan Makin | F377: kevan.makin@belhaven.co.uk | G377: Graham Baird | H377: Eden | I377: Cumbria
A378: CA18 | B378: Roy Knox | C378: 709 | D378: royknox@greeneking.co.uk | E378: Kevan Makin | F378: kevan.makin@belhaven.co.uk | G378: Graham Baird | H378: Scotland | I378: Scotland
A379: CA19 | B379: Roy Knox | C379: 709 | D379: royknox@greeneking.co.uk | E379: Kevan Makin | F379: kevan.makin@belhaven.co.uk | G379: Graham Baird | H379: Scotland | I379: Scotland
A380: CA2 | B380: Roy Knox | C380: 709 | D380: royknox@greeneking.co.uk | E380: Kevan Makin | F380: kevan.makin@belhaven.co.uk | G380: Graham Baird | H380: Carlisle | I380: Cumbria
... A1016: GU9 | B1016: Dan Gathercole | C1016: 210 | D1016: danielgathercole@greeneking.co.uk | E1016: Paul Rogers | F1016: paulrogers@greeneking.co.uk | G1016: Scott Russell | H1016: Waverley | I1016: Surrey
A1017: GY1 | B1017: Out of area | C1017: OOA | E1017: Out of Area | F1017: Out of Area | G1017: Out of Area | H1017: Unknown | I1017: Unknown
A1018: GY10 | B1018: Out of area | C1018: OOA | E1018: Out of Area | F1018: Out of Area | G1018: Out of Area | H1018: Unknown | I1018: Unknown
A1019: GY2 | B1019: Out of area | C1019: OOA | E1019: Out of Area | F1019: Out of Area | G1019: Out of Area | H1019: Unknown | I1019: Unknown
A1020: GY3 | B1020: Out of area | C1020: OOA | E1020: Out of Area | F1020: Out of Area | G1020: Out of Area | H1020: Unknown | I1020: Unknown
A1021: GY4 | B1021: Out of area | C1021: OOA | E1021: Out of Area | F1021: Out of Area | G1021: Out of Area | H1021: Unknown | I1021: Unknown
A1022: GY5 | B1022: Out of area | C1022: OOA | E1022: Out of Area | F1022: Out of Area | G1022: Out of Area | H1022: Unknown | I1022: Unknown
A1023: GY6 | B1023: Out of area | C1023: OOA | E1023: Out of Area | F1023: Out of Area | G1023: Out of Area | H1023: Unknown | I1023: Unknown
A1024: GY7 | B1024: Out of area | C1024: OOA | E1024: Out of Area | F1024: Out of Area | G1024: Out of Area | H1024: Unknown | I1024: Unknown
A1025: GY8 | B1025: Out of area | C1025: OOA | E1025: Out of Area | F1025: Out of Area | G1025: Out of Area | H1025: Unknown | I1025: Unknown
A1026: GY9 | B1026: Out of area | C1026: OOA | E1026: Out of Area | F1026: Out of Area | G1026: Out of Area | H1026: Unknown | I1026: Unknown
A1027: HA0 | B1027: Ade Kamson | C1027: 224 | D1027: adekamson@greeneking.co.uk | E1027: Paul Rogers | F1027: paulrogers@greeneking.co.uk | G1027: Scott Russell | H1027: Brent | I1027: Outer London
A1028: HA1 | B1028: Tom Brindley | C1028: 228 | D1028: TomBrindley@greeneking.co.uk | E1028: Gary Simpson | F1028: garysimpson@greeneking.co.uk | G1028: Scott Russell | H1028: Harrow | I1028: Outer London
A1029: HA2 | B1029: Tom Brindley | C1029: 228 | D1029: TomBrindley@greeneking.co.uk | E1029: Gary Simpson | F1029: garysimpson@greeneking.co.uk | G1029: Scott Russell | H1029: Harrow | I1029: Outer London
A1030: HA3 | B1030: Tom Brindley | C1030: 228 | D1030: TomBrindley@greeneking.co.uk | E1030: Gary Simpson | F1030: garysimpson@greeneking.co.uk | G1030: Scott Russell | H1030: Brent | I1030: Outer London
A1031: HA4 | B1031: Tom Brindley | C1031: 228 | D1031: TomBrindley@greeneking.co.uk | E1031: Gary Simpson | F1031: garysimpson@greeneking.co.uk | G1031: Scott Russell | H1031: Hillingdon | I1031: Outer London
A1032: HA5 | B1032: Tom Brindley | C1032: 228 | D1032: TomBrindley@greeneking.co.uk | E1032: Gary Simpson | F1032: garysimpson@greeneking.co.uk | G1032: Scott Russell | H1032: Harrow | I1032: Outer London
A1033: HA6 | B1033: Tom Brindley | C1033: 228 | D1033: TomBrindley@greeneking.co.uk | E1033: Gary Simpson | F1033: garysimpson@greeneking.co.uk | G1033: Scott Russell | H1033: Hillingdon | I1033: Outer London
A1034: HA7 | B1034: Tom Brindley | C1034: 228 | D1034: TomBrindley@greeneking.co.uk | E1034: Gary Simpson | F1034: garysimpson@greeneking.co.uk | G1034: Scott Russell | H1034: Harrow | I1034: Outer London
A1035: HA8 | B1035: Tom Brindley | C1035: 228 | D1035: TomBrindley@greeneking.co.uk | E1035: Gary Simpson | F1035: garysimpson@greeneking.co.uk | G1035: Scott Russell | H1035: Barnet | I1035: Outer London
A1036: HA9 | B1036: Ade Kamson | C1036: 224 | D1036: adekamson@greeneking.co.uk | E1036: Paul Rogers | F1036: paulrogers@greeneking.co.uk | G1036: Scott Russell | H1036: Brent | I1036: Outer London
A1037: HD1 | B1037: Jessica Green | C1037: 235 | D1037: jessicagreen@greeneking.co.uk | E1037: Liam Hancy | F1037: liamhancy@greeneking.co.uk | G1037: Scott Russell | H1037: Kirklees | I1037: West Yorkshire
A1038: HD2 | B1038: Jessica Green | C1038: 235 | D1038: jessicagreen@greeneking.co.uk | E1038: Liam Hancy | F1038: liamhancy@greeneking.co.uk | G1038: Scott Russell | H1038: Kirklees | I1038: West Yorkshire
... A1083: HR9 | B1083: Craig Barry | C1083: 234 | D1083: craigbarry@greeneking.co.uk | E1083: Alan Dawson | F1083: AlanDawson@greeneking.co.uk | G1083: Scott Russell | H1083: Herefordshire | I1083: Herefordshire
A1084: HS1 | B1084: Out of area | C1084: OOA | E1084: Out of Area | F1084: Out of Area | G1084: Out of Area | H1084: Unknown | I1084: Unknown
A1085: HS2 | B1085: Out of area | C1085: OOA | E1085: Out of Area | F1085: Out of Area | G1085: Out of Area | H1085: Unknown | I1085: Unknown
A1086: HS3 | B1086: Out of area | C1086: OOA | E1086: Out of Area | F1086: Out of Area | G1086: Out of Area | H1086: Unknown | I1086: Unknown
A1087: HS4 | B1087: Out of area | C1087: OOA | E1087: Out of Area | F1087: Out of Area | G1087: Out of Area | H1087: Unknown | I1087: Unknown
A1088: HS5 | B1088: Out of area | C1088: OOA | E1088: Out of Area | F1088: Out of Area | G1088: Out of Area | H1088: Unknown | I1088: Unknown
A1089: HS6 | B1089: Out of area | C1089: OOA | E1089: Out of Area | F1089: Out of Area | G1089: Out of Area | H1089: Unknown | I1089: Unknown
A1090: HS7 | B1090: Out of area | C1090: OOA | E1090: Out of Area | F1090: Out of Area | G1090: Out of Area | H1090: Unknown | I1090: Unknown
A1091: HS8 | B1091: Out of area | C1091: OOA | E1091: Out of Area | F1091: Out of Area | G1091: Out of Area | H1091: Unknown | I1091: Unknown
A1092: HS9 | B1092: Out of area | C1092: OOA | E1092: Out of Area | F1092: Out of Area | G1092: Out of Area | H1092: Unknown | I1092: Unknown
A1093: HU1 | B1093: Alastair Drew | C1093: 231 | D1093: AlastairDrew@greeneking.co.uk | E1093: Liam Hancy | F1093: liamhancy@greeneking.co.uk | G1093: Scott Russell | H1093: Kingston upon Hull, City of | I1093: East Riding of Yorkshire
A1094: HU10 | B1094: Alastair Drew | C1094: 231 | D1094: AlastairDrew@greeneking.co.uk | E1094: Liam Hancy | F1094: liamhancy@greeneking.co.uk | G1094: Scott Russell | H1094: Unknown | I1094: Unknown
A1095: HU11 | B1095: Alastair Drew | C1095: 231 | D1095: AlastairDrew@greeneking.co.uk | E1095: Liam Hancy | F1095: liamhancy@greeneking.co.uk | G1095: Scott Russell | H1095: East Riding of Yorkshire | I1095: East Riding of Yorkshire
A1096: HU12 | B1096: Alastair Drew | C1096: 231 | D1096: AlastairDrew@greeneking.co.uk | E1096: Liam Hancy | F1096: liamhancy@greeneking.co.uk | G1096: Scott Russell | H1096: East Riding of Yorkshire | I1096: East Riding of Yorkshire
A1097: HU13 | B1097: Alastair Drew | C1097: 231 | D1097: AlastairDrew@greeneking.co.uk | E1097: Liam Hancy | F1097: liamhancy@greeneking.co.uk | G1097: Scott Russell | H1097: East Riding of Yorkshire | I1097: East Riding of Yorkshire
A1098: HU14 | B1098: Alastair Drew | C1098: 231 | D1098: AlastairDrew@greeneking.co.uk | E1098: Liam Hancy | F1098: liamhancy@greeneking.co.uk | G1098: Scott Russell | H1098: East Riding of Yorkshire | I1098: East Riding of Yorkshire
A1099: HU15 | B1099: Alastair Drew | C1099: 231 | D1099: AlastairDrew@greeneking.co.uk | E1099: Liam Hancy | F1099: liamhancy@greeneking.co.uk | G1099: Scott Russell | H1099: East Riding of Yorkshire | I1099: East Riding of Yorkshire
A1100: HU16 | B1100: Alastair Drew | C1100: 231 | D1100: AlastairDrew@greeneking.co.uk | E1100: Liam Hancy | F1100: liamhancy@greeneking.co.uk | G1100: Scott Russell | H1100: East Riding of Yorkshire | I1100: East Riding of Yorkshire
A1101: HU17 | B1101: Alastair Drew | C1101: 231 | D1101: AlastairDrew@greeneking.co.uk | E1101: Liam Hancy | F1101: liamhancy@greeneking.co.uk | G1101: Scott Russell | H1101: East Riding of Yorkshire | I1101: East Riding of Yorkshire
A1102: HU18 | B1102: Alastair Drew | C1102: 231 | D1102: AlastairDrew@greeneking.co.uk | E1102: Liam Hancy | F1102: liamhancy@greeneking.co.uk | G1102: Scott Russell | H1102: East Riding of Yorkshire | I1102: East Riding of Yorkshire
A1103: HU19 | B1103: Alastair Drew | C1103: 231 | D1103: AlastairDrew@greeneking.co.uk | E1103: Liam Hancy | F1103: liamhancy@greeneking.co.uk | G1103: Scott Russell | H1103: East Riding of Yorkshire | I1103: East Riding of Yorkshire
A1104: HU2 | B1104: Alastair Drew | C1104: 231 | D1104: AlastairDrew@greeneking.co.uk | E1104: Liam Hancy | F1104: liamhancy@greeneking.co.uk | G1104: Scott Russell | H1104: Kingston upon Hull, City of | I1104: East Riding of Yorkshire
... A1130: IG9 | B1130: David Williamson | C1130: 202 | D1130: davidwilliamson@greeneking.co.uk | E1130: Gary Simpson | F1130: garysimpson@greeneking.co.uk | G1130: Scott Russell | H1130: Epping Forest | I1130: Essex
A1131: IM1 | B1131: Out of area | C1131: OOA | E1131: Out of Area | F1131: Out of Area | G1131: Out of Area | H1131: Unknown | I1131: Unknown
A1132: IM2 | B1132: Out of area | C1132: OOA | E1132: Out of Area | F1132: Out of Area | G1132: Out of Area | H1132: Unknown | I1132: Unknown
A1133: IM3 | B1133: Out of area | C1133: OOA | E1133: Out of Area | F1133: Out of Area | G1133: Out of Area | H1133: Unknown | I1133: Unknown
A1134: IM4 | B1134: Out of area | C1134: OOA | E1134: Out of Area | F1134: Out of Area | G1134: Out of Area | H1134: Unknown | I1134: Unknown
A1135: IM5 | B1135: Out of area | C1135: OOA | E1135: Out of Area | F1135: Out of Area | G1135: Out of Area | H1135: Unknown | I1135: Unknown
A1136: IM6 | B1136: Out of area | C1136: OOA | E1136: Out of Area | F1136: Out of Area | G1136: Out of Area | H1136: Unknown | I1136: Unknown
A1137: IM7 | B1137: Out of area | C1137: OOA | E1137: Out of Area | F1137: Out of Area | G1137: Out of Area | H1137: Unknown | I1137: Unknown
A1138: IM8 | B1138: Out of area | C1138: OOA | E1138: Out of Area | F1138: Out of Area | G1138: Out of Area | H1138: Unknown | I1138: Unknown
A1139: IM9 | B1139: Out of area | C1139: OOA | E1139: Out of Area | F1139: Out of Area | G1139: Out of Area | H1139: Unknown | I1139: Unknown
A1140: IP1 | B1140: Kate Rayson | C1140: 225 | D1140: katerayson@greeneking.co.uk | E1140: Tom Brown | F1140: tombrown@greeneking.co.uk | G1140: Scott Russell | H1140: Ipswich | I1140: Suffolk
A1141: IP10 | B1141: Rob Brown | C1141: 206 | D1141: Robertbrown@greeneking.co.uk | E1141: Tom Brown | F1141: tombrown@greeneking.co.uk | G1141: Scott Russell | H1141: East Suffolk | I1141: Suffolk
A1142: IP11 | B1142: Rob Brown | C1142: 206 | D1142: Robertbrown@greeneking.co.uk | E1142: Tom Brown | F1142: tombrown@greeneking.co.uk | G1142: Scott Russell | H1142: Suffolk Coastal | I1142: Suffolk
A1143: IP12 | B1143: Rob Brown | C1143: 206 | D1143: Robertbrown@greeneking.co.uk | E1143: Tom Brown | F1143: tombrown@greeneking.co.uk | G1143: Scott Russell | H1143: Suffolk Coastal | I1143: Suffolk
A1144: IP13 | B1144: Rob Brown | C1144: 206 | D1144: Robertbrown@greeneking.co.uk | E1144: Tom Brown | F1144: tombrown@greeneking.co.uk | G1144: Scott Russell | H1144: Suffolk Coastal | I1144: Suffolk
A1145: IP14 | B1145: Kate Rayson | C1145: 225 | D1145: katerayson@greeneking.co.uk | E1145: Tom Brown | F1145: tombrown@greeneking.co.uk | G1145: Scott Russell | H1145: Mid Suffolk | I1145: Suffolk
...

Sheet Base

Sheet Multi Op LL
A1: Group | B1: POC | C1: zip | D1: district | E1: mngr/owner | F1: RTM | G1: email | H1: phone | I1: Notes
A2: distinct group | B2: cantley cock | C2: nr13 3jq | D2: =_xlfn.TEXTBEFORE(C2, " ") -> nr13 | I2: hells in may, sm always
A3: distinct group | B3: hatfield | C3: nr33 0qg | D3: =_xlfn.TEXTBEFORE(C3, " ") -> nr33 | I3: sm always - no hells
A4: distinct group | B4: kerrys | C4: nr2 4tl | D4: =_xlfn.TEXTBEFORE(C4, " ") -> nr2 | I4: hells and sm in aprl
A5: distinct group | B5: butcher bhoy | C5: nr2 1at | D5: =_xlfn.TEXTBEFORE(C5, " ") -> nr2 | I5: hells and sm in aprl
A6: distinct group | B6: stag | C6: NR13 6RW | D6: =_xlfn.TEXTBEFORE(C6, " ") -> NR13 | I6: sm in aprl - no hells
A7: distinct group | B7: oaklands | C7: NR7 0HH | D7: =_xlfn.TEXTBEFORE(C7, " ") -> NR7 | I7: hells in aprl and sm always
A8: distinct group | B8: sole and heel | C8: NR13 6QH | D8: =_xlfn.TEXTBEFORE(C8, " ") -> NR13 | I8: hells in aprl and sm feb
A9: moss and co | B9: henham barns | C9: NR34 8AQ | D9: =_xlfn.TEXTBEFORE(C9, " ") -> NR34 | F9: GK IFT | I9: no bbg
A10: moss and co | B10: angel | C10: nr34 8rl | D10: =_xlfn.TEXTBEFORE(C10, " ") -> nr34 | E10: amelia and eliza | F10: GK IFT | I10: san mig and stella on -(didn’t see stella on last, but on vols-missed?) carlsberg dip, ops for BL?
A11: moss and co | B11: bell | C11: nr33 8jr | D11: =_xlfn.TEXTBEFORE(C11, " ") -> nr33 | E11: harley gm baily am | F11: GK IFT | I11: sm on, and stella -(didn’t see stella on last, but on vols- missed?) replace with adnams
A12: moss and co | B12: harbour | C12: nr33 0ag | D12: =_xlfn.TEXTBEFORE(C12, " ") -> nr33 | F12: GK IFT | I12: stella and sm on
A13: moss and co | B13: jolly sailors | C13: nr33 0js | D13: =_xlfn.TEXTBEFORE(C13, " ") -> nr33 | E13: adam mngr, sarah am | F13: GK IFT | I13: SM and Stella on - Hells and BL on mobile
A14: moss and co | B14: broadlands | C14: NR33 9JY | D14: =_xlfn.TEXTBEFORE(C14, " ") -> NR33 | E14: abby mngr tina am | F14: GK IFT | I14: sanmig and stella pouring -hells ops, packaged is good
A15: moss and co | B15: vilage maid | C15: NR32 5LP | D15: =_xlfn.TEXTBEFORE(C15, " ") -> NR32 | E15: rachel gm, kyle am | F15: GK IFT | I15: Sm on, no stella but any ops?
A16: moss and co | B16: white horse | C16: IP13 8JR | D16: =_xlfn.TEXTBEFORE(C16, " ") -> IP13 | E16: niki tender, em gm | F16: GK IFT | I16: stella and sm on, stella was on churn watch, bobbie said ops for kop
A17: moss and co | B17: Commodore | C17: NR32 3NF | D17: =_xlfn.TEXTBEFORE(C17, " ") -> NR32 | E17: Tom mngr, bobbie ho | F17: Stonegate
A18: Norwich Inns | B18: Alexandra Tavern | C18: NR2 3BB | D18: =_xlfn.TEXTBEFORE(C18, " ") -> NR2 | E18: Craig McLaren CEO | F18: ift | G18: secretary@norwichinns.co.uk | H18: 07799 530152 01603 627772 | I18: https://www.norwichinns.com/ flag from sdm, working on propsoal
A19: Norwich Inns | B19: Annesley House Hotel, Norwich | C19: nr2 2la | D19: =_xlfn.TEXTBEFORE(C19, " ") -> nr2 | E19: Craig McLaren CEO
A20: Norwich Inns | B20: Black Boys Hotel | C20: nr11 6eh | D20: =_xlfn.TEXTBEFORE(C20, " ") -> nr11 | E20: Craig McLaren CEO | H20: 01263 732122
A21: Norwich Inns | B21: Blue Boar | C21: nr7 8rl | D21: =_xlfn.TEXTBEFORE(C21, " ") -> nr7 | E21: Craig McLaren CEO | H21: 1603426802
A22: Norwich Inns | B22: Brick Kilns | C22: nr13 5jh | D22: =_xlfn.TEXTBEFORE(C22, " ") -> nr13 | E22: Craig McLaren CEO | H22: (01603) 720043
A23: Norwich Inns | B23: California Tavern | C23: nr29 3qw | D23: =_xlfn.TEXTBEFORE(C23, " ") -> nr29 | E23: Craig McLaren CEO | H23: 01493 730340
A24: Norwich Inns | B24: Coach & Horses | C24: nr1 1ba | D24: =_xlfn.TEXTBEFORE(C24, " ") -> nr1 | E24: Craig McLaren CEO | H24: 1603477077
A25: Norwich Inns | B25: Countryman | C25: nr15 1ns | D25: =_xlfn.TEXTBEFORE(C25, " ") -> nr15 | E25: Craig McLaren CEO | H25: 01508 470946
A26: Norwich Inns | B26: Dales Hotel | C26: nr26 8tj | D26: =_xlfn.TEXTBEFORE(C26, " ") -> nr26 | E26: Craig McLaren CEO | H26: 01263 824555
A27: Norwich Inns | B27: Dog Inn | C27: nr29 5ny | D27: =_xlfn.TEXTBEFORE(C27, " ") -> nr29 | E27: Craig McLaren CEO | H27: 01692 631041
A28: Norwich Inns | B28: Dolphin Club | C28: nr29 4jd | D28: =_xlfn.TEXTBEFORE(C28, " ") -> nr29 | E28: Craig McLaren CEO
A29: Norwich Inns | B29: Eaton Golf Club | C29: nr4 6sf | D29: =_xlfn.TEXTBEFORE(C29, " ") -> nr4 | E29: Craig McLaren CEO | H29: 01603 251395
A30: Norwich Inns | B30: Furzedown Hotel | C30: NR30 4EN | D30: =_xlfn.TEXTBEFORE(C30, " ") -> NR30 | E30: Craig McLaren CEO | H30: 01493 844138
A31: Norwich Inns | B31: George Hotel. Norwich | C31: NR2 2DA | D31: =_xlfn.TEXTBEFORE(C31, " ") -> NR2 | E31: Craig McLaren CEO | H31: 1603617841
A32: Norwich Inns | B32: Glen Lodge Bawburgh Golf Club | C32: NR9 3LU | D32: =_xlfn.TEXTBEFORE(C32, " ") -> NR9 | E32: Craig McLaren CEO
A33: Norwich Inns | B33: Kings Arms | C33: NR30 1BG | D33: =_xlfn.TEXTBEFORE(C33, " ") -> NR30 | E33: Craig McLaren CEO
A34: Norwich Inns | B34: Kings Head Bawburgh | C34: NR9 3LS | D34: =_xlfn.TEXTBEFORE(C34, " ") -> NR9 | E34: Craig McLaren CEO | H34: 01603 744977
A35: Norwich Inns | B35: Kings Head, Loddon | C35: NR14 6EZ | D35: =_xlfn.TEXTBEFORE(C35, " ") -> NR14 | E35: Craig McLaren CEO | H35: 01508 520330
A36: Norwich Inns | B36: Kings Head. Ashwellthorpe | C36: NR12 7EA | D36: =_xlfn.TEXTBEFORE(C36, " ") -> NR12 | E36: Craig McLaren CEO | H36: 01603 737426
A37: Norwich Inns | B37: Links Hotel | C37: NR27 9QH | D37: =_xlfn.TEXTBEFORE(C37, " ") -> NR27 | E37: Craig McLaren CEO | H37: 01263 838383
A38: Norwich Inns | B38: Merlins | C38: NR30 2EJ | D38: =_xlfn.TEXTBEFORE(C38, " ") -> NR30 | E38: Craig McLaren CEO
A39: Norwich Inns | B39: Park Farm Hotel | C39: NR9 3DL | D39: =_xlfn.TEXTBEFORE(C39, " ") -> NR9 | E39: Craig McLaren CEO | H39: 01603 810264
A40: Norwich Inns | B40: Pier Hotel | C40: NR31 6PL | D40: =_xlfn.TEXTBEFORE(C40, " ") -> NR31 | E40: Craig McLaren CEO | H40: 01493 662631
A41: Norwich Inns | B41: Pleasure Beach Inn | C41: NR30 3EH | D41: =_xlfn.TEXTBEFORE(C41, " ") -> NR30 | E41: Craig McLaren CEO
A42: Norwich Inns | B42: Prom Hotel | C42: NR30 2DH | D42: =_xlfn.TEXTBEFORE(C42, " ") -> NR30 | E42: Craig McLaren CEO | H42: 01493 842308
A43: Norwich Inns | B43: Queens Head | C43: NR9 3QB | D43: =_xlfn.TEXTBEFORE(C43, " ") -> NR9 | E43: Craig McLaren CEO | H43: 01603 810226
A44: Norwich Inns | B44: Recruiting Sergeant | C44: NR12 7EE | D44: =_xlfn.TEXTBEFORE(C44, " ") -> NR12 | E44: Craig McLaren CEO | H44: 01603 737077 | I44: is this not colchester inns????
A45: Norwich Inns | B45: Red Lion, Eaton | C45: nR4 7LD | D45: =_xlfn.TEXTBEFORE(C45, " ") -> nR4 | E45: Craig McLaren CEO
A46: Norwich Inns | B46: Ribs of Beef Riverside Freehouse | C46: NR3 1HY | D46: =_xlfn.TEXTBEFORE(C46, " ") -> NR3 | E46: Craig McLaren CEO | H46: 01603 619517
A47: Norwich Inns | B47: Richmond Park Golf Club | C47: IP25 6EA | D47: =_xlfn.TEXTBEFORE(C47, " ") -> IP25 | E47: Craig McLaren CEO | H47: 01953 881803
A48: Norwich Inns | B48: Salhouse Lodge | C48: NR13 6HD | D48: =_xlfn.TEXTBEFORE(C48, " ") -> NR13 | E48: Craig McLaren CEO | H48: 01603 782828
A49: Norwich Inns | B49: Seamarge Hotel | C49: NR27 0AB | D49: =_xlfn.TEXTBEFORE(C49, " ") -> NR27 | E49: Craig McLaren CEO | H49: 01263 579579
A50: Norwich Inns | B50: Shoulder of Mutton | C50: NR13 4NT | D50: =_xlfn.TEXTBEFORE(C50, " ") -> NR13 | E50: Craig McLaren CEO | H50: (01603) 926530
A51: Norwich Inns | B51: Temple Bar | C51: NR2 2RA | D51: =_xlfn.TEXTBEFORE(C51, " ") -> NR2 | E51: Craig McLaren CEO
A52: Norwich Inns | B52: The 12 Lost Churches | C52: IP17 3DQ | D52: =_xlfn.TEXTBEFORE(C52, " ") -> IP17 | E52: Craig McLaren CEO | H52: 01728 648282
A53: Norwich Inns | B53: The Buckinghamshire Arms | C53: NR11 6NF | D53: =_xlfn.TEXTBEFORE(C53, " ") -> NR11 | E53: Craig McLaren CEO | I53: is this not colchester inns????
A54: Norwich Inns | B54: The Eagle PH | C54: NR2 2HN | D54: =_xlfn.TEXTBEFORE(C54, " ") -> NR2 | E54: Craig McLaren CEO | H54: 01603 624173
A55: Norwich Inns | B55: The Hotel Victoria | C55: NR33 0BZ | D55: =_xlfn.TEXTBEFORE(C55, " ") -> NR33 | E55: Craig McLaren CEO | H55: +44 (0) 1502 574433
A56: Norwich Inns | B56: The Murderers | C56: NR1 3LB | D56: =_xlfn.TEXTBEFORE(C56, " ") -> NR1 | E56: Craig McLaren CEO | H56: 01603 621 447
A57: Norwich Inns | B57: The Old Hall Hotel, Caister-On-Sea | C57: NR30 5JL | D57: =_xlfn.TEXTBEFORE(C57, " ") -> NR30 | E57: Craig McLaren CEO | H57: (0)1493 720400
A58: Norwich Inns | B58: The Sandsgate | C58: NR29 4JE | D58: =_xlfn.TEXTBEFORE(C58, " ") -> NR29 | E58: Craig McLaren CEO | H58: 01493 730023
A59: Norwich Inns | B59: Unthank Arms Restaurant and Bar | C59: NR2 2DR | D59: =_xlfn.TEXTBEFORE(C59, " ") -> NR2 | E59: Craig McLaren CEO | H59: 01603 631557 | I59: is this the cricketers??????
A60: Norwich Inns | B60: Vernon Arms | C60: NR11 8NP | D60: =_xlfn.TEXTBEFORE(C60, " ") -> NR11 | E60: Craig McLaren CEO | H60: 01263 833355
A61: Norwich Inns | B61: Waggon & Horses | C61: IP25 6QD | D61: =_xlfn.TEXTBEFORE(C61, " ") -> IP25 | E61: Craig McLaren CEO | H61: 01953 883847
A62: Norwich Inns | B62: Warwick Arms | C62: NR2 3LD | D62: =_xlfn.TEXTBEFORE(C62, " ") -> NR2 | E62: Craig McLaren CEO | H62: 01603 627687
A63: Norwich Inns | B63: Wellington Hotel | C63: NR27 9HN | D63: =_xlfn.TEXTBEFORE(C63, " ") -> NR27 | E63: Craig McLaren CEO
A64: Norwich Inns | B64: Whalebone Freehouse | C64: NR3 4BA | D64: =_xlfn.TEXTBEFORE(C64, " ") -> NR3 | E64: Craig McLaren CEO | H64: 01603 425482
A65: Norwich Inns | B65: Whitwell & Reepham Railway Complex | C65: NR10 4GA | D65: =_xlfn.TEXTBEFORE(C65, " ") -> NR10 | E65: Craig McLaren CEO | H65: 01603 871694
A66: Norwich Inns | B66: Wig & Pen | C66: NR3 1RN | D66: =_xlfn.TEXTBEFORE(C66, " ") -> NR3 | E66: Craig McLaren CEO | H66: 01603 625891
A67: Norwich Inns | B67: William IV | C67: NR1 4AU | D67: =_xlfn.TEXTBEFORE(C67, " ") -> NR1 | E67: Craig McLaren CEO | H67: 01603 441526
A68: Stout and Stone Inns | B68: Oak Tree | C68: nr4 6la | D68: =_xlfn.TEXTBEFORE(C68, " ") -> nr4 | E68: Danny | F68: STONEGATE | G68: oaktree@stoutandstoneinns.co.uk | H68: tel:01603362642 | I68: outside of patch https://www.stoutandstoneinns.com/our-pubs
A69: Snug Inns | B69: White Lodge (Attleborough) | C69: NR17 1AY | D69: =_xlfn.TEXTBEFORE(C69, " ") -> NR17 | E69: Daniel Pratt OWNER -LUCY MNGR | F69: STONEGATE | G69: pub@thewhitelodgeattleborough.co.uk | H69: 01953 528988
A70: Snug Inns | B70: Queens Head (Hethersett) | C70: NR9 3DD | D70: =_xlfn.TEXTBEFORE(C70, " ") -> NR9 | E70: Richard & Michael - CHARLOTTE ON SITE | F70: STONEGATE | G70: pub@thequeensheadthurlton.co.uk | H70: 01603 559 599 | I70: PERHAPS RICHARD AND MICHAEL NO LONGER?
A71: Snug Inns | B71: The Kings Head - Acle Steakhouse | C71: NR13 3DY | D71: =_xlfn.TEXTBEFORE(C71, " ") -> NR13 | E71: NATALIE | F71: STONEGATE | G71: pub@thekingsheadacle.co.uk | H71: 01603 559 599 | I71: CORONA ON
A72: Snug Inns | B72: Woodman | C72: NR6 7QA | D72: =_xlfn.TEXTBEFORE(C72, " ") -> NR6 | E72: RYAN | F72: WAM? | G72: pub@thewoodmanoldcatton.co.uk | H72: 01603 559 599
A73: Snug Inns | B73: Crown | C73: NR12 9AD | D73: =_xlfn.TEXTBEFORE(C73, " ") -> NR12 | E73: DARREN | F73: WAM? | G73: pub@thecrownsmallburgh.co.uk | H73: 01603 559 599
A74: Snug Inns | B74: Freemasons Arms | C74: NR1 3HQ | D74: =_xlfn.TEXTBEFORE(C74, " ") -> NR1 | E74: Charlotte | F74: WAM? | G74: pub@thefreemasonsarmsnorwich.co.uk | H74: 01603 559 599
A75: Snug Inns | B75: Rose & Crown | C75: PE31 6TW | D75: =_xlfn.TEXTBEFORE(C75, " ") -> PE31 | E75: Warren | F75: WAM? | G75: pub@theroseandcrownharopley.co.uk | H75: 01485 521807
A76: Snug Inns | B76: Nelson | C76: NR2 4DR | D76: =_xlfn.TEXTBEFORE(C76, " ") -> NR2 | E76: Crystal | F76: Stonegate | G76: pub@thenelsonnorwich.co.uk | H76: 01603 559 599 | I76: was paul, new to snug - corona going on
A77: Keighly & Patrick | B77: Wortwell Bell (Wortwell) | C77: IP20 0HH | D77: =_xlfn.TEXTBEFORE(C77, " ") -> IP20 | E77: Keighly & Patrick | F77: STONEGATE
A78: Keighly & Patrick | B78: Dickleburgh Crown (Dickleburgh) | C78: IP21 4NQ | D78: =_xlfn.TEXTBEFORE(C78, " ") -> IP21 | E78: Keighly & Patrick | F78: STONEGATE
A79: Colchester Inns | B79: Black Boys (Aylsham) | C79: NR11 6EH | D79: =_xlfn.TEXTBEFORE(C79, " ") -> NR11 | E79: Matt Colchester | F79: STONEGATE | G79: admin@blackboyshotel.co.uk matt.blackboyshotel@hotmail.com | H79: 01263 732122
A80: Colchester Inns | B80: Recruiting Sergeant | C80: NR12 7EE | D80: =_xlfn.TEXTBEFORE(C80, " ") -> NR12 | E80: Nicola | F80: ? | G80: nicola@recruitingsergeant.co.uk | H80: 01603 737077 | I80: is this norwich inns now???????????
A81: Colchester Inns | B81: Rising Sun | C81: NR12 7EA | D81: =_xlfn.TEXTBEFORE(C81, " ") -> NR12 | E81: Andy | F81: STONEGATE | G81: manager@risingsuncoltishall.co.uk | H81: 01603 737440 | I81: tried corning andy, didn't respond to my comms re removing amdri... maybe adnams rep won this one... no changes yet and andy not in ran into the adnams rep here. recieved new tbars from huk for line up, contract over and open to taking off madri and amstwl has 3 other pubs, black boy leased is one
A82: Colchester Inns | B82: Bucks Arms | C82: NR11 6NF | D82: =_xlfn.TEXTBEFORE(C82, " ") -> NR11 | F82: ? | G82: manager@bucksarms.co.uk | H82: 01263 732133 | I82: is this norwich inns now???????????
A83: Colchester Inns | B83: The Lodge at Salhouse | C83: NR13 6HD | D83: =_xlfn.TEXTBEFORE(C83, " ") -> NR13 | E83: George | F83: ? | G83: george@salhouselodge.co.uk manager@salhouselodge.co.uk | H83: 01603 928181
A84: Colchester Inns | B84: Swan | C84: NR8 6AB | D84: =_xlfn.TEXTBEFORE(C84, " ") -> NR8 | E84: Andy | F84: ? | G84: andy@swanatringland.co.uk manager@swanatringland.co.uk | H84: 01603 572736
A85: Jason Barker? | B85: White Swan (North Walsham) | C85: NR28 9DA | D85: =_xlfn.TEXTBEFORE(C85, " ") -> NR28 | E85: Jason Barker owner? Mark mngr? | F85: STONEGATE | H85: 1692500006 | I85: lots of bbg packaged ops for core brands and san mig. not craftybat all low priority but revisit when booked in town
A86: Wendy Smuts | B86: Black Horse | C86: IP1 2EF | D86: =_xlfn.TEXTBEFORE(C86, " ") -> IP1 | E86: Wendy Smuts | F86: STONEGATE | H86: 7542000421 | I86: Pale on, hells ops. - birth place of cardenal wolsey. Stuart is rm happy to push hells, emailing for aid. amstel did a dip but more apt to remove fosters.... wants SP for not SP pricing tho. rose sticking to current line up, and likes to keep them the same. to busy for chat fu apt week after 15th Wendy is leaser- 7542000421 owned 1.5years pale glasses stubby request Norwich rose opening on 2nd - wants to keep offering the same - letting the other pub open and then perhaps hells (reminder for next month check in emailing activation options to push hells most beers on 60/40 pale had a co2 fitted curiosity gas is hells ? just weary about work, though we do it for them
A87: Wendy Smuts | B87: Norwich Rose | C87: nr2 2at | D87: =_xlfn.TEXTBEFORE(C87, " ") -> nr2 | E87: Wendy Smuts | F87: STONEGATE | G87: info@therosepubanddeli.co.uk | H87: 01603 623 942 | I87: Oldest trading pub in norwich
A88: Steve & Andy | B88: brewers arms | C88: ip1 3ns | D88: =_xlfn.TEXTBEFORE(C88, " ") -> ip1 | E88: Steve & Andy | F88: Admiral
A89: Steve & Andy | B89: Walnut Tree | C89: IP14 1NE | D89: =_xlfn.TEXTBEFORE(C89, " ") -> IP14 | E89: Steve & Andy | F89: Admiral
A90: Cricketers | B90: Crown | C90: co11 1ah | D90: =_xlfn.TEXTBEFORE(C90, " ") -> co11 | E90: Matt | F90: GK L&T
A91: Cricketers | B91: Alma | C91: Co6 1bz | D91: =_xlfn.TEXTBEFORE(C91, " ") -> Co6 | E91: Matt | F91: GK L&T
A92: Cricketers | B92: Cricketers | C92: CO3 9TG | D92: =_xlfn.TEXTBEFORE(C92, " ") -> CO3 | E92: Matt | F92: GK L&T | I92: is this norwich inns????
A93: Cricketers | B93: Unthank Arms | C93: NR2 2DR | D93: =_xlfn.TEXTBEFORE(C93, " ") -> NR2 | E93: Nick
A94: i2i hospitality | B94: Drawing Rooms | C94: NR2 1DS | D94: =_xlfn.TEXTBEFORE(C94, " ") -> NR2 | E94: Pete Harvey DIRECTOR -Matteo gm, Austin am | G94: drawingrooms@i2ihospitality.co.uk
A95: i2i hospitality | B95: The Wildman | C95: NR2 1AG | D95: =_xlfn.TEXTBEFORE(C95, " ") -> NR2 | F95: ? | G95: wildman@i2ihospitality.co.uk
A96: i2i hospitality | B96: The Hero (burnham Overy Staithe | C96: PE31 8JE | D96: =_xlfn.TEXTBEFORE(C96, " ") -> PE31 | F96: ? | G96: info@theheroburnhamovery.co.uk | H96: 1328738334
A97: i2i hospitality | B97: Ten Bells | C97: NR2 4AR | D97: =_xlfn.TEXTBEFORE(C97, " ") -> NR2 | F97: ? | G97: tenbells@i2ihospitality.co.uk

Sheet CAT

Sheet Ox. Brewers Ipswich
C2: Ipswhich | D2: 2024 | E2: 2025 | G2: September 24 v 25 | L2: Hells
C3: BBG Market Share | D3: 0.072996257 | E3: 0.068302981 | L3: +17.5% Pints YOY
B5: BDM | C5: Ipswhich | D5: 2024 | F5: 2025
D6: Pints | E6: Stockists | F6: Pints | G6: % change v 24 | H6: Stockists | I6: % change v 24
B7: TOTAL | C7: Total Draught Sales | D7: 6621783.4 | E7: 215 | F7: 6500258 | G7: -0.018352367 | H7: 215 | I7: -1
C8: Total Draught Beer | D8: 6011868.1 | E8: 215 | F8: 5884139 | G8: -0.021246158 | H8: 215 | I8: -1
C9: Total BBG | D9: 483365.4 | E9: 100 | F9: 443987 | G9: -0.081467147 | H9: 90 | I9: -11
C10: Total CMBC | D10: 553047.4 | E10: 95 | F10: 509190.8 | G10: -0.079299894 | H10: 103 | I10: 7
C11: Total Molson Coors | D11: 1158371.3 | E11: 172 | F11: 969650.3 | G11: -0.16291926 | H11: 156 | I11: -17
C12: Total Heineken UK | D12: 2139576.1 | E12: 194 | F12: 2303465.2 | G12: 0.076598865 | H12: 198 | I12: 3
C13: Total All Other | D13: 2287416.4 | E13: 214 | F13: 2273949.5 | G13: -0.0058873846 | H13: 214 | I13: -1
B14: CORE LAGER | C14: Total Lager | D14: 3706048.8 | E14: 215 | F14: 3613502.4 | G14: -0.024971717 | H14: 215 | I14: -1
C15: Total Core Lager | D15: 887698.1 | E15: 137 | F15: 769456.4 | G15: -0.13320035 | H15: 136 | I15: -2
C16: Total Bud Light | D16: 1455.7 | E16: 1 | H16: 0 | I16: -2
C17: Total Carling | D17: 149133.3 | E17: 32 | F17: 115488.2 | G17: -0.22560421 | H17: 28 | I17: -5
C18: Total Carlsberg Pilsner | D18: 223880.5 | E18: 38 | F18: 199734.4 | G18: -0.10785263 | H18: 41 | I18: 2
C19: Total Fosters | D19: 504205.3 | E19: 88 | F19: 444722.5 | G19: -0.11797337 | H19: 85 | I19: -4
C20: Total Tennents Lager | E20: 0 | H20: 0 | I20: -1
B21: PREMIUM 4% | C21: Total World 4% | D21: 443418.2 | E21: 109 | F21: 386535.3 | G21: -0.12828274 | H21: 109 | I21: -1
C22: Total Amstel | D22: 222533 | E22: 55 | F22: 214966.1 | G22: -0.034003496 | H22: 64 | I22: 8
C23: Total Becks Vier | D23: 16436.4 | E23: 4 | F23: 8847.6 | G23: -0.46170694 | H23: 4 | I23: -1
C24: Total Coors | D24: 135976.2 | E24: 34 | F24: 97493.1 | G24: -0.2830135 | H24: 24 | I24: -11
C25: Total Grolsch 4% | E25: 0 | H25: 0 | I25: -1
C26: Total Heineken Silver | D26: 2288.7 | E26: 1 | F26: 441.9 | G26: -0.80692096 | H26: 0 | I26: -2
C27: Total Kozel | E27: 0 | H27: 0 | I27: -1
C28: Total Pravha | D28: 66183.4 | E28: 21 | F28: 64786.6 | G28: -0.02110499 | H28: 22 | I28: 0
B29: PREMIUM LAGER | C29: Total Premium Lager | D29: 619091.4 | E29: 114 | F29: 595424.6 | G29: -0.038228281 | H29: 118 | I29: 3
C30: Total Budweiser | D30: 14992 | E30: 5 | F30: 9411.5 | G30: -0.37223186 | H30: 2 | I30: -4
C31: Total Carlsberg Export | D31: 233864 | E31: 42 | F31: 218752.9 | G31: -0.064614904 | H31: 40 | I31: -3
C32: Total Heineken | D32: 69973.9 | E32: 24 | F32: 75620.4 | G32: 0.080694373 | H32: 24 | I32: -1
C33: Total Kronenbourg 1664 | D33: 83805.8 | E33: 19 | F33: 74861.5 | G33: -0.1067265 | H33: 25 | I33: 5
C34: Total San Miguel | D34: 196150.9 | E34: 48 | F34: 174336 | G34: -0.11121489 | H34: 36 | I34: -13
C35: Total Stella Artois | D35: 216451.5 | E35: 50 | F35: 216774.8 | G35: 0.0014936371 | H35: 54 | I35: 3
B36: WORLD LAGER | C36: Total World Beer | D36: 1755829.3 | E36: 212 | F36: 1862078.8 | G36: 0.060512431 | H36: 212 | I36: -1
C37: Total Asahi | D37: 24460 | E37: 5 | F37: 24004.2 | G37: -0.018634505 | H37: 6 | I37: 0
C38: Total Birra Moretti | D38: 646122.6 | E38: 136 | F38: 656705.6 | G38: 0.016379244 | H38: 138 | I38: 1
C39: Total Camden Hells Lager | D39: 14994.5 | E39: 8 | F39: 17611.2 | G39: 0.17451065 | H39: 12 | I39: 3
C40: Total Cobra | D40: 428.7 | E40: 0 | H40: 0 | I40: -1
C41: Total Corona Extra | D41: 5755.2 | E41: 3 | F41: 2591.4 | G41: -0.54972894 | H41: 4 | I41: 0
C42: Total Estrella Damm | D42: 65483.2 | E42: 13 | F42: 46210.2 | G42: -0.29431976 | H42: 16 | I42: 2
C43: Total Madri | D43: 406248.4 | E43: 95 | F43: 329433.2 | G43: -0.18908431 | H43: 79 | I43: -17
C44: Total Mahou | E44: 0 | H44: 0 | I44: -1
C45: Total Peroni Nastro Azzurro | D45: 48737.2 | E45: 14 | F45: 59409.8 | G45: 0.21898263 | H45: 17 | I45: 2
C46: Total Pilsner Urquell | E46: 0 | H46: 0 | I46: -1
C47: Total Red Stripe | D47: 4346 | E47: 4 | F47: 18827.5 | G47: 3.3321445 | H47: 7 | I47: 2
C48: Total Sagres | E48: 0 | H48: 0 | I48: -1
C49: Total Staropramen | D49: 29457.9 | E49: 12 | F49: 30433.3 | G49: 0.033111661 | H49: 14 | I49: 1
C50: Total Tiger | D50: 1295.8 | E50: 1 | F50: 834.7 | G50: -0.35584195 | H50: 0 | I50: -2
B51: CRAFT LAGER | C51: Total Spec/Craft Lager | D51: 64425.6 | E51: 40 | F51: 63428.7 | G51: -0.015473663 | H51: 40 | I51: -1
C52: Total Hoegaarden | E52: 0 | H52: 0 | I52: -1
C53: Total Leffe Blonde | E53: 0 | H53: 0 | I53: -1
B54: ALE & STOUT | C54: Total Ale | D54: 1318297 | E54: 203 | F54: 1175159.5 | G54: -0.10857758 | H54: 194 | I54: -10
C55: Total Spec / Craft Ale | D55: 248437.7 | E55: 116 | F55: 279005.1 | G55: 0.12303849 | H55: 130 | I55: 13
C56: Total Standard Ale | D56: 125426.3 | E56: 69 | F56: 110022.5 | G56: -0.12281156 | H56: 59 | I56: -11
C57: Total Premium Ale | D57: 4124.8 | E57: 1 | F57: 3875 | G57: -0.060560512 | H57: 2 | I57: 0
C58: Total Cask Ale | D58: 1188736.5 | E58: 185 | F58: 1061252.9 | G58: -0.10724294 | H58: 179 | I58: -7
C59: Total Beavertown Neck Oil | D59: 142908.5 | E59: 72 | F59: 156983.2 | G59: 0.098487494 | H59: 68 | I59: -5
C60: Total Brewdog Punk IPA | D60: 587.1 | E60: 1 | F60: 717.2 | G60: 0.22159768 | H60: 1 | I60: -1
C61: Total Camden Town Pale Ale | D61: 10485.7 | E61: 9 | F61: 10217.6 | G61: -0.025568155 | H61: 8 | I61: -2
C62: Total Goose Island IPA | E62: 0 | H62: 0 | I62: -1
C63: Total Innis & Gunn IPA | E63: 0 | H63: 0 | I63: -1
C64: Total Long Horn IPA | E64: 0 | H64: 0 | I64: -1
C65: Total Sharps Atlantic Pale | E65: 0 | H65: 0 | I65: -1
C66: Total Shipyard Rye Pale Ale | E66: 0 | H66: 0 | I66: -1
C67: Total Stout | D67: 674648.9 | E67: 205 | F67: 753018.9 | G67: 0.11616413 | H67: 212 | I67: 6
B68: TOTAL CIDER | C68: Total Cider | D68: 609910 | E68: 210 | F68: 616116.5 | G68: 0.010176092 | H68: 208 | I68: -3
C69: Total Apple Cider | D69: 505380.8 | E69: 210 | F69: 516196.2 | G69: 0.021400496 | H69: 207 | I69: -4
C70: Total Aspalls Cyder | D70: 336507.3 | E70: 137 | F70: 304450.5 | G70: -0.095263312 | H70: 120 | I70: -18
C71: Total Kingston Press | E71: 0 | H71: 0 | I71: -1
C72: Total Magners Draught | D72: 2150.7 | E72: 2 | F72: 537.3 | G72: -0.75017436 | H72: 1 | I72: -2
C73: Total Orchard Thieves | D73: 848.3 | E73: 1 | F73: 1391.7 | G73: 0.64057527 | H73: 2 | I73: 0
C74: Total Strongbow | D74: 33520.4 | E74: 21 | F74: 28249 | G74: -0.15725946 | H74: 17 | I74: -5
C75: Total Strongbow Cloudy Apple | E75: 0 | H75: 0 | I75: -1
C76: Total Stowford Press | D76: 597.4 | E76: 2 | F76: 55.3 | G76: -0.90743221 | H76: 1 | I76: -2
C77: Total Symonds Founders Reserve | E77: 0 | H77: 0 | I77: -1
C78: Total Thatchers Gold | D78: 16749.5 | E78: 8 | F78: 11265.8 | G78: -0.32739485 | H78: 6 | I78: -3
C79: Total Thatchers Dry | E79: 0 | H79: 0 | I79: -1
C80: Total Thatchers Haze | D80: 3060.6 | E80: 3 | F80: 1515.4 | G80: -0.50486833 | H80: 1 | I80: -3
C81: Total Flavoured Cider | D81: 104519.4 | E81: 83 | F81: 99916.7 | G81: -0.044036801 | H81: 76 | I81: -8
C82: Total Carling Black Fruits | D82: 3686.3 | E82: 3 | F82: 739.2 | G82: -0.79947373 | H82: 1 | I82: -3
C83: Total Kopparberg Raspberry Cider | E83: 0 | H83: 0 | I83: -1
C84: Total Magners Draught Dark Fruit | D84: 6339.4 | E84: 8 | F84: 4107.5 | G84: -0.35206802 | H84: 4 | I84: -5
C85: Total Old Mout Berry | D85: 31187.2 | E85: 29 | F85: 45582.6 | G85: 0.46158039 | H85: 34 | I85: 4
C86: Total Strongbow Dark Fruit | D86: 60379.9 | E86: 39 | F86: 43288.3 | G86: -0.28306771 | H86: 29 | I86: -11

Sheet Ox. Brewers All Patches
A1: Oxford Partnership | Monthly BDM Volumes Tracker YTD
A2: Source: Oxford Market Watch | Volumes Tracker (September 2025 ) | O2: BDM | P2: 2024 | Q2: 2025
O3: BBG Market Share | P3: 0.051252919 | Q3: 0.047677269
A4: © The Oxford Partnership Limited 2025
O5: Birmingham | P5: 0.043408923 | Q5: 0.038286454
O6: Bournemouth | P6: 0.069194017 | Q6: 0.06569989
O7: Bristol | P7: 0.046398515 | Q7: 0.046686891
O8: Cambridge / Home Counties | P8: 0.076356892 | Q8: 0.073232704
J9: Camden Pale | K9: Mahou | L9: Bud Light | M9: Stella Artois | O9: Cardiff | P9: 0.081842083 | Q9: 0.076331625
B10: (All) | C10: 2024 | D10: 2025 | J10: +11% Pints YOY | K10: +400% Pints YOY | L10: +37.3% Pints YOY | M10: +4.5% Pint vs Moretti YOY | O10: Edinburgh / Glasgow | P10: 0.017579566 | Q10: 0.016178909
B11: BBG Market Share | C11: 0.051252919 | D11: 0.047677269 | J11: Punk -28% | K11: EstrellaD -12.2% | L11: CARLS -10.3% | M11: +3.7% Pint vs HUK YOY | O11: Exeter | P11: 0.046153675 | Q11: 0.028592319
J12: Neckoil -11% | K12: Madri -14.8% | L12: Calring -12% | O12: Ipswhich | P12: 0.072996257 | Q12: 0.068302981
A13: BDM | B13: (All) | C13: 2024 | E13: 2025 | L13: Fosters -11.3% | O13: Leeds & York | P13: 0.032407228 | Q13: 0.028396956
C14: Pints | D14: Stockists | E14: Pints | F14: % change v 24 | G14: Stockists | H14: % change v 24 | O14: Leicester | P14: 0.049390634 | Q14: 0.04638525
A15: TOTAL | B15: Total Draught Sales | C15: 3.1254079e+08 | D15: 8315 | E15: 3.0120319e+08 | F15: -0.03627559 | G15: 8146 | H15: -169 | O15: Liverpool | P15: 0.049617583 | Q15: 0.050016743
B16: Total Draught Beer | C16: 2.8093009e+08 | D16: 8312 | E16: 2.6998843e+08 | F16: -0.038947985 | G16: 8144 | H16: -168 | O16: Manchester | P16: 0.054458544 | Q16: 0.050752933
B17: Total BBG | C17: 16018628 | D17: 3134 | E17: 14360546 | F17: -0.10350964 | G17: 2691 | H17: -443 | O17: Newcastle | P17: 0.04716445 | Q17: 0.045636982
B18: Total CMBC | C18: 9355299.8 | D18: 1987 | E18: 9093699.6 | F18: -0.027962781 | G18: 2071 | H18: 84 | O18: North London | P18: 0.058969087 | Q18: 0.051544093
B19: Total Molson Coors | C19: 65275950 | D19: 5546 | E19: 56944375 | F19: -0.12763622 | G19: 5290 | H19: -256 | O19: Nottingham | P19: 0.052296451 | Q19: 0.043491484
B20: Total Heineken UK | C20: 1.0770079e+08 | D20: 7657 | E20: 1.0696427e+08 | F20: -0.0068385525 | G20: 7561 | H20: -96 | O20: Reading | P20: 0.045816082 | Q20: 0.043491484
B21: Total All Other | C21: 1.1418978e+08 | D21: 8217 | E21: 1.1383916e+08 | F21: -0.0030704518 | G21: 8049 | H21: -168 | O21: Sheffield | P21: 0.04943343 | Q21: 0.049934006
A22: CORE LAGER | B22: Total Lager | C22: 1.761406e+08 | D22: 8292 | E22: 167665470 | F22: -0.048115723 | G22: 8122 | H22: -170 | O22: South London | P22: 0.062246764 | Q22: 0.062134626
B23: Total Core Lager | C23: 68309799 | D23: 6476 | E23: 61078714 | F23: -0.10585722 | G23: 6260 | H23: -216 | O23: Southampton | P23: 0.054214283 | Q23: 0.054551717
B24: Total Bud Light | C24: 21826.8 | D24: 7 | E24: 29962.6 | F24: 0.3727436 | G24: 12 | H24: 5 | O24: Truro | P24: 0.050528123 | Q24: 0.019332983
B25: Total Carling | C25: 32917625 | D25: 3665 | E25: 28957905 | F25: -0.12029177 | G25: 3484 | H25: -181
B26: Total Carlsberg Pilsner | C26: 2476603.7 | D26: 441 | E26: 2222127.8 | F26: -0.10275197 | G26: 458 | H26: 17
B27: Total Fosters | C27: 25447024 | D27: 3263 | E27: 22575373 | F27: -0.11284821 | G27: 3100 | H27: -163
B28: Total Tennents Lager | C28: 6889335.5 | D28: 375 | E28: 6678194.6 | F28: -0.030647499 | G28: 360 | H28: -15
A29: PREMIUM 4% | B29: Total World 4% | C29: 23183877 | D29: 4834 | E29: 19782741 | F29: -0.14670266 | G29: 4390 | H29: -444
B30: Total Amstel | C30: 9990738.6 | D30: 2417 | E30: 9059362.8 | F30: -0.093223918 | G30: 2299 | H30: -118
B31: Total Becks Vier | C31: 157992.7 | D31: 40 | E31: 123215 | F31: -0.2201222 | G31: 31 | H31: -9
B32: Total Coors | C32: 10584640 | D32: 2038 | E32: 8556331.1 | F32: -0.19162758 | G32: 1754 | H32: -284
B33: Total Grolsch 4% | C33: 23881.4 | D33: 8 | E33: 23885.9 | F33: 0.00018843116 | G33: 13 | H33: 5
B34: Total Heineken Silver | C34: 342811 | D34: 142 | E34: 71268.8 | F34: -0.79210469 | G34: 5 | H34: -137
B35: Total Kozel | C35: 0 | D35: 0 | E35: 0 | F35: 0 | G35: 0 | H35: 0
B36: Total Pravha | C36: 2074048.6 | D36: 523 | E36: 1927002.5 | F36: -0.070898098 | G36: 512 | H36: -11
A37: PREMIUM LAGER | B37: Total Premium Lager | C37: 17466646 | D37: 3528 | E37: 16805373 | F37: -0.03785922 | G37: 3539 | H37: 11
B38: Total Budweiser | C38: 131253.4 | D38: 43 | E38: 122606.8 | F38: -0.065877151 | G38: 37 | H38: -6
B39: Total Carlsberg Export | C39: 1976826.2 | D39: 357 | E39: 1835532.4 | F39: -0.071475075 | G39: 347 | H39: -10
B40: Total Heineken | C40: 3386888 | D40: 982 | E40: 3168372 | F40: -0.064518224 | G40: 1019 | H40: 37
B41: Total Kronenbourg 1664 | C41: 3526785.3 | D41: 853 | E41: 3510402.6 | F41: -0.0046452218 | G41: 1003 | H41: 150
B42: Total San Miguel | C42: 5729886.2 | D42: 1137 | E42: 4334185.9 | F42: -0.24358255 | G42: 776 | H42: -361
B43: Total Stella Artois | C43: 7894130 | D43: 1615 | E43: 7670847.7 | F43: -0.028284599 | G43: 1523 | H43: -92
A44: WORLD LAGER | B44: Total World Beer | C44: 67179978 | D44: 7815 | E44: 69989019 | F44: 0.041813653 | G44: 7735 | H44: -80
B45: Total Asahi | C45: 660577.9 | D45: 186 | E45: 908336.8 | F45: 0.37506386 | G45: 251 | H45: 65
B46: Total Birra Moretti | C46: 27244987 | D46: 5250 | E46: 25247525 | F46: -0.073314844 | G46: 5158 | H46: -92
B47: Total Camden Hells Lager | C47: 758521.9 | D47: 319 | E47: 729929.8 | F47: -0.037694495 | G47: 288 | H47: -31
B48: Total Cobra | C48: 167434.9 | D48: 56 | E48: 181868.6 | F48: 0.086204847 | G48: 72 | H48: 16
B49: Total Corona Extra | C49: 262536.6 | D49: 136 | E49: 241782.7 | F49: -0.079051454 | G49: 119 | H49: -17
B50: Total Estrella Damm | C50: 1377722.9 | D50: 259 | E50: 1209338.4 | F50: -0.12221942 | G50: 247 | H50: -12
B51: Total Madri | C51: 13626631 | D51: 2671 | E51: 11604136 | F51: -0.14842227 | G51: 2350 | H51: -321
B52: Total Mahou | C52: 4596.2 | D52: 2 | E52: 22997 | F52: 4.0034811 | G52: 15 | H52: 13
B53: Total Peroni Nastro Azzurro | C53: 2304312.7 | D53: 499 | E53: 2240841.7 | F53: -0.027544439 | G53: 476 | H53: -23
B54: Total Pilsner Urquell | C54: 7078.7 | D54: 7 | E54: 7701.1 | F54: 0.087925749 | G54: 6 | H54: -1
B55: Total Red Stripe | C55: 993294.7 | D55: 261 | E55: 1246223.2 | F55: 0.25463591 | G55: 345 | H55: 84
B56: Total Sagres | C56: 30362.4 | D56: 8 | E56: 25864 | F56: -0.14815693 | G56: 7 | H56: -1
... B58: Total Tiger | C58: 26134.1 | D58: 14 | E58: 17084.3 | F58: -0.34628321 | G58: 9 | H58: -5
A59: CRAFT LAGER | B59: Total Spec/Craft Lager | C59: 2819844.9 | D59: 1106 | E59: 3148896.6 | F59: 0.11669142 | G59: 1186 | H59: 80
B60: Total Hoegaarden | C60: 1457.4 | D60: 2 | E60: 488.9 | F60: -0.66453959 | G60: 0 | H60: -2
B61: Total Leffe Blonde | C61: 34803.4 | D61: 32 | E61: 30975.7 | F61: -0.10998063 | G61: 24 | H61: -8
A62: ALE & STOUT | B62: Total Ale | C62: 60223501 | D62: 7844 | E62: 55477538 | F62: -0.078805833 | G62: 7625 | H62: -219
B63: Total Standard Ale | C63: 15827308 | D63: 4198 | E63: 14067072 | F63: -0.11121515 | G63: 3904 | H63: -294
B64: Total Cask Ale | C64: 43886841 | D64: 6201 | E64: 40956807 | F64: -0.066763383 | G64: 6049 | H64: -152
B65: Total Premium Ale | C65: 508941.9 | D65: 211 | E65: 439406.1 | F65: -0.13662817 | G65: 174 | H65: -37
B66: Total Spec / Craft Ale | C66: 9444311.8 | D66: 3834 | E66: 8903779.1 | F66: -0.057233678 | G66: 3873 | H66: 39
B67: Total Brewdog Punk IPA | C67: 23595.3 | D67: 15 | E67: 16955 | F67: -0.28142469 | G67: 16 | H67: 1
B68: Total Camden Town Pale Ale | C68: 458690.6 | D68: 379 | E68: 509163.8 | F68: 0.11003757 | G68: 358 | H68: -21
B69: Total Beavertown Neck Oil | C69: 5599253.5 | D69: 2410 | E69: 4983939.2 | F69: -0.1098922 | G69: 2193 | H69: -217
B70: Total Innis & Gunn IPA | C70: 181859.3 | D70: 41 | E70: 151647.5 | F70: -0.16612733 | G70: 34 | H70: -7
B71: Total Goose Island IPA | C71: 333.6 | D71: 1 | E71: 0 | F71: 0 | G71: 0 | H71: -1
B72: Total Long Horn IPA | C72: 2265.1 | D72: 0 | E72: 313.1 | F72: -0.86177211 | G72: 0 | H72: 0
B73: Total Sharps Atlantic Pale | C73: 25794.7 | D73: 20 | E73: 21634.8 | F73: -0.16126956 | G73: 14 | H73: -6
B74: Total Shipyard Rye Pale Ale | C74: 12117.6 | D74: 7 | E74: 11374.5 | F74: -0.061324025 | G74: 9 | H74: 2
B75: Total Stout | C75: 32301350 | D75: 7874 | E75: 34792212 | F75: 0.077113248 | G75: 7869 | H75: -5
A76: TOTAL CIDER | B76: Total Cider | C76: 31610593 | D76: 8082 | E76: 31214670 | F76: -0.012525026 | G76: 7909 | H76: -173
B77: Total Apple Cider | C77: 26596156 | D77: 8043 | E77: 26565328 | F77: -0.0011591036 | G77: 7871 | H77: -172
B78: Total Aspalls Cyder | C78: 2426270.3 | D78: 1115 | E78: 2449353.8 | F78: 0.0095139853 | G78: 1092 | H78: -23
B79: Total Kingston Press | C79: 204.5 | D79: 0 | E79: 0 | F79: 0 | G79: 0 | H79: 0
B80: Total Magners Draught | C80: 198216.6 | D80: 147 | E80: 164948.3 | F80: -0.16783811 | G80: 104 | H80: -43
B81: Total Orchard Thieves | C81: 495447.1 | D81: 225 | E81: 359051.7 | F81: -0.2752976 | G81: 173 | H81: -52
B82: Total Strongbow | C82: 6209595.5 | D82: 2450 | E82: 5475036.9 | F82: -0.11829411 | G82: 2195 | H82: -255
B83: Total Strongbow Cloudy Apple | C83: 15103.2 | D83: 5 | E83: 10253.9 | F83: -0.32107765 | G83: 4 | H83: -1
B84: Total Stowford Press | C84: 1233133.4 | D84: 506 | E84: 977183.6 | F84: -0.20756051 | G84: 410 | H84: -96
B85: Total Symonds Founders Reserve | C85: 5296.3 | D85: 3 | E85: 5050 | F85: -0.046504163 | G85: 2 | H85: -1
B86: Total Thatchers Gold | C86: 5133059.4 | D86: 1340 | E86: 4942874.7 | F86: -0.037050945 | G86: 1312 | H86: -28
B87: Total Thatchers Dry | C87: 207977.4 | D87: 78 | E87: 193543.9 | F87: -0.069399367 | G87: 74 | H87: -4
B88: Total Thatchers Haze | C88: 1196511.4 | D88: 537 | E88: 1077736.7 | F88: -0.099267504 | G88: 501 | H88: -36
... B94: Total Strongbow Dark Fruit | C94: 2879526.8 | D94: 1886 | E94: 2172769.6 | F94: -0.24544213 | G94: 1468 | H94: -418

Sheet Push

Sheet Pipeline, RM Push, Visit Ops
A1: outlet_name | B1: zipcode | C1: sector | D1: district | E1: RTM | F1: RM | G1: Landlords | H1: email | I1: contact | J1: Group? | K1: Notes | L1: Brand in | M1: why - staci/lead/rm/whoopsie | N1: BDM TODO
A2: Angel | B2: NR34 8RL | C2: =LEFT(B2,2) -> NR | D2: =_xlfn.TEXTBEFORE(B2, " ") -> NR34 | E2: GK IFT | F2: adam vass | G2: Eliza & amelia | I2: 770107725 | K2: later afternoons best, Thursdays better. prebook carlberg had a vol dip perhaps ops for bl. not tied fully to gk. | M2: lead mid | N2: call visit
A3: attleboro football | B3: nr17 2as | C3: =LEFT(B3,2) -> nr | D3: =_xlfn.TEXTBEFORE(B3, " ") -> nr17 | E3: Greene King | F3: reddit | G3: emma | I3: 44 7584 073258 | K3: £121.36+VAT for tnt | M3: install fu | N3: want tnt?
A4: bath house | B4: co14 8pz | C4: =LEFT(B4,2) -> co | D4: =_xlfn.TEXTBEFORE(B4, " ") -> co14 | E4: Greene King | F4: nikki | G4: kish | M4: install fu
A5: belle vue | B5: nr2 3bl | C5: =LEFT(B5,2) -> nr | D5: =_xlfn.TEXTBEFORE(B5, " ") -> nr2 | E5: Stonegate | F5: Galloway | G5: david | I5: 7545340923 | J5: y | K5: golden thorpe group (and cellar house). Wants mahoue ipo madri (modelo and eazy also in talks as of dec. 1) | L5: eazy/mahou | M5: lead high
A6: Belstead Arms | B6: IP2 9QU | C6: =LEFT(B6,2) -> IP | D6: =_xlfn.TEXTBEFORE(B6, " ") -> IP2 | E6: Stonegate | F6: pitt | G6: Emma and Darren (penny sister) | I6: 07707859243 | M6: lead low
A7: Bull | B7: NR19 1DZ | C7: =LEFT(B7,2) -> NR | D7: =_xlfn.TEXTBEFORE(B7, " ") -> NR19 | E7: greene King IFT | F7: JARVIS | G7: nigel | I7: 7920113861 | K7: pale installing ipo Level - lvm x2 nov 26 | M7: install fu
A8: Cock Horse | B8: CO10 9SA | C8: =LEFT(B8,2) -> CO | D8: =_xlfn.TEXTBEFORE(B8, " ") -> CO10 | E8: Stonegate | G8: kev and becca | H8: info@thecockhorse.co.uk | J8: y | K8: very sp site, not really tnt, bella pubs (previously not replyed via email/phone Bunbury arms ip33, linden tree ip33- both (gk l&t), and three kings inn -fornham all saints | M8: lead low
A9: Crown | B9: ip14 4bq | C9: =LEFT(B9,2) -> ip | D9: =_xlfn.TEXTBEFORE(B9, " ") -> ip14 | E9: gk ift | G9: lee | M9: install fu
A10: Crown | B10: CO11 1AH | C10: =LEFT(B10,2) -> CO | D10: =_xlfn.TEXTBEFORE(B10, " ") -> CO11 | E10: GK L&T | F10: Pearson | G10: Matt | J10: y | K10: Stella likely, works at alma. Rm push promised | L10: Stella | M10: lead mid
A11: falcon | B11: ip11 9ds | C11: =LEFT(B11,2) -> ip | D11: =_xlfn.TEXTBEFORE(B11, " ") -> ip11 | E11: Admiral | F11: mciver | M11: lead low | N11: rm help
A12: four horseshoes | B12: ip23 8hd | C12: =LEFT(B12,2) -> ip | D12: =_xlfn.TEXTBEFORE(B12, " ") -> ip23 | E12: GK IFT | F12: rob brown | G12: tom | K12: SM new in march, stella ipo reti ops - call | M12: install fu | N12: rm help
A13: Fox | B13: ip31 1rd | C13: =LEFT(B13,2) -> ip | D13: =_xlfn.TEXTBEFORE(B13, " ") -> ip31 | E13: gk ift | F13: kate | G13: harrison | K13: tnt pending, stella new… open ops | M13: install fu | N13: tnt/lead fu
A14: Garden House | B14: nr16 2by | C14: =LEFT(B14,2) -> nr | D14: =_xlfn.TEXTBEFORE(B14, " ") -> nr16 | E14: gk ift | F14: adam vass | K14: aka smokehouse, churned and back | M14: install fu
A15: Glen Lodge Golf and Wedding Center | B15: NR9 3LU | C15: =LEFT(B15,2) -> NR | D15: =_xlfn.TEXTBEFORE(B15, " ") -> NR9 | E15: Greene King | G15: lou | H15: lou@bawburgh.com | M15: lead mid
A16: golden star | B16: nr3 1dd | C16: =LEFT(B16,2) -> nr | D16: =_xlfn.TEXTBEFORE(B16, " ") -> nr3 | E16: GK L&T | F16: Jarvis | G16: Leva | I16: 7897305379 | K16: leva - leva to wahts app me a good date for next week , as on holiday this. call to confirm visit next Thursday after 5 . Stella best fit - but says no? happy for a chat but more kop btl and 0%... Push camden light ops (data lead) | M16: lead mid
A17: Greyhound (Lavenham) | B17: CO10 9PZ | C17: =LEFT(B17,2) -> CO | D17: =_xlfn.TEXTBEFORE(B17, " ") -> CO10 | E17: GK L&T | G17: sally | H17: info@greyhoundlavenham.co.uk | K17: Sally in tomorrow, (Keighley?) tender shared email to book in. slammed for mid day and good vibes. ops for fruit cider swap to stella or hells. | M17: lead low
A18: Hare Inn Long Melford | B18: CO10 9DF | C18: =LEFT(B18,2) -> CO | D18: =_xlfn.TEXTBEFORE(B18, " ") -> CO10 | E18: GK L&T | F18: Sam | G18: nik and kate | K18: rose is kates sister. - either can be dm. tori tender checked upstairs but kate is out. haven't changed up the bar since I was here this time LY. emailing. Peroni ops | M18: lead low
A19: Hintlesham Community Hall | B19: ip8 3ps | C19: =LEFT(B19,2) -> ip | D19: =_xlfn.TEXTBEFORE(B19, " ") -> ip8 | E19: gk ift | G19: jim | I19: 7768462492 | M19: install fu
A20: Horringer Social Club | B20: ip29 5ru | C20: =LEFT(B20,2) -> ip | D20: =_xlfn.TEXTBEFORE(B20, " ") -> ip29 | E20: gk ift | G20: John | I20: 07802 912704 | K20: hells installed | M20: install fu
A21: Hudson | B21: CO1 1NX | C21: =LEFT(B21,2) | D21: =_xlfn.TEXTBEFORE(B21, " ") -> CO1 | E21: gk ift | F21: joe sagnella | G21: henry | I21: 7974132616 | K21: also o n churn? | L21: becks oct flag | M21: install confirm
A22: Kings arms | B22: CO7 7DJ | E22: Stonegate | K22: 2 foc frome harry | M22: protect
A23: Kings Head | B23: CO10 0JE | C23: =LEFT(B23,2) -> CO | D23: =_xlfn.TEXTBEFORE(B23, " ") -> CO10 | E23: GK L&T | F23: Sam | M23: lead low
A24: Lifeboat | B24: NR12 0AL | C24: =LEFT(B24,2) -> NR | D24: =_xlfn.TEXTBEFORE(B24, " ") -> NR12 | E24: GK IFT | F24: Galpin | G24: Matt | K24: customer lvm with landline, tried twice lvm no resposne. Has SM | M24: lead mid
A25: Mouse trap | B25: nr1 1bg | C25: =LEFT(B25,2) -> nr | D25: =_xlfn.TEXTBEFORE(B25, " ") -> nr1 | E25: gk ift | K25: site not on google? Sdm reddit? | L25: stella & becks on dec flags | M25: install confirm
A26: norfolk terrier | B26: IP24 1TA | C26: =LEFT(B26,2) -> IP | D26: =_xlfn.TEXTBEFORE(B26, " ") -> IP24 | E26: GK L&T | F26: Jarvis | G26: Tish | I26: 7799491049 | K26: HIVE TO LEASED IN FEB | L26: Stella | M26: lead low
A27: Old Red House | B27: NR33 8JP | C27: =LEFT(B27,2) -> NR | D27: =_xlfn.TEXTBEFORE(B27, " ") -> NR33 | E27: Stonegate | G27: TINA | I27: 7780430669 | K27: Tina on hols until sept 27, one carling drinker, has x3 coor to attack dupes, neckoil does well but ££, no tnt but ops as just too costly | M27: lead mid
A28: Old times | B28: IP4 5NJ | C28: ip | D28: =_xlfn.TEXTBEFORE(B28, " ") -> IP4 | E28: GK IFT | F28: Kate | M28: protect | N28: tnt cancelled?
A29: Parkhill Hotel | B29: NR32 5DQ | C29: =LEFT(B29,2) -> NR | D29: =_xlfn.TEXTBEFORE(B29, " ") -> NR32 | E29: CMBC | F29: Rob | G29: Ruth pwmer (noel daughters wife and bar manager) | H29: mail@parkhillhotel.co.uk | K29: function weeks- 32pints in one pod- uses 6-7 pods (estrella mainly).. 3 kegs a week outside of events. noel is married to the daughter of the owners. from Pennsylvania. met her wife at Disney and moved here. she's happy for a meet to explore options. feels the carlsberg Dispense system is limited on choice to be able to switch up. sanmig sold well but delisted on the Dispense system and estrella is much more ££...but volumes are the same. worried to remove Dispense system. as goes through little volumes and saves on wastage. but up to explore. will share with sdm and see ops, not likely to be of worth for gk tbd. lots of packaged options and easier for them. | M29: lead mid | N29: rm fu
A30: Plough | B30: NR32 5AN | C30: =LEFT(B30,2) -> NR | D30: =_xlfn.TEXTBEFORE(B30, " ") -> NR32 | E30: PROSPECT IFT | F30: Rob | G30: dan ll a nd Dawn tender | H30: info@ploughinn-blundeston.co.uk | J30: y | K30: has three other pubs: bell st olives the priory (seasonal pub)- opposite the bell. Wavley river center - towards Beccles alpaca newest, inches new ipo aspall. cruz and oil top vol, the cask. | M30: lead mid
A31: Pot Black | B31: ip33 1yq | C31: =LEFT(B31,2) -> ip | D31: =_xlfn.TEXTBEFORE(B31, " ") -> ip33 | E31: gk ift | F31: kate | G31: andy | K31: tnt sorted on $? Vianet is sorted. Screenprojecter requested w fraser | L31: bl ipo cmbc | M31: lead high | N31: tnt price sorted?
A32: queens head stowmarket | B32: IP14 1EF | C32: =LEFT(B32,2) -> IP | D32: =_xlfn.TEXTBEFORE(B32, " ") -> IP14 | E32: punch | G32: michael and d | I32: 7702177636 | K32: stella on - sm off in jan ipo cruz. Open to stout ipo guin…or next to for foc, and fancy differiancion…x 1/2 keg a week of G remove -or if dear, atlantic doing no sells and do both stouts for trail and margin play -rm require postbox | L32: stout | M32: lead high | N32: lead fu
A33: Rose & Crown Hotel | B33: CO1 2TZ | C33: =LEFT(B33,2) -> CO | D33: =_xlfn.TEXTBEFORE(B33, " ") -> CO1 | E33: CMBC | F33: nikki | G33: ilza | H33: ilze.iriste@rose-and-crown.com | K33: ealza. is bar manager and wedding manager... walked in whilst a bride was walking down the isle.... lots of crying. reception says she's super easy going and likely to chat, sending email off cmbc list. couldn't see bar as wedding, tbd | M33: lead low
A34: Royal British Legion Club | B34: IP14 1PH | C34: =LEFT(B34,2) -> IP | D34: =_xlfn.TEXTBEFORE(B34, " ") -> IP14 | E34: Greene King | G34: kelly bar manager (sue secratary) | M34: lead mid | N34: get quotes
A35: Royal George | B35: IP31 1DD | C35: =LEFT(B35,2) -> IP | D35: =_xlfn.TEXTBEFORE(B35, " ") -> IP31 | E35: Admiral | G35: bob and nick | K35: asked to fu ops in early november | M35: lead mid
A36: sailors home | B36: nr33 7sb | C36: =LEFT(B36,2) -> nr | D36: =_xlfn.TEXTBEFORE(B36, " ") -> nr33 | E36: gk ift | K36: has sm on font, gk led pub | L36: becks in dec flags | M36: install confirm
A37: seaspan | B37: co15 1un | C37: =LEFT(B37,2) -> co | D37: =_xlfn.TEXTBEFORE(B37, " ") -> co15 | E37: Greene King | F37: nikki | G37: chris | M37: install fu
A38: Swan Hotel Lavenham | B38: CO10 9QA | C38: =LEFT(B38,2) -> CO | D38: =_xlfn.TEXTBEFORE(B38, " ") -> CO10 | E38: PROSPECT IFT | G38: james sanders gm- gillian bar mngr dm | H38: gillian.murgia@theswanatlavenham.co.uk | J38: y | K38: freddy, very quiet shy youngster behind the bar. doesn't know much of the trading vibe but passed on email for mngr and sending email. has a x3 joints, others are restraunt and spa. tbd on ops | M38: lead low
A39: Swan Inn | B39: IP21 5AS | C39: =LEFT(B39,2) -> IP | D39: =_xlfn.TEXTBEFORE(B39, " ") -> IP21 | E39: Stonegate | F39: pitt | G39: new management tbd | M39: lead low | N39: rm help
A40: swan | B40: ip21 5pe | C40: =LEFT(B40,2) -> ip | D40: =_xlfn.TEXTBEFORE(B40, " ") -> ip21 | E40: gk ift | G40: mick | I40: 73941740453 | K40: san mig ipo madri, new accout | M40: install fu
A41: Swan Inn | B41: IP6 9AJ | C41: =LEFT(B41,2) -> IP | D41: =_xlfn.TEXTBEFORE(B41, " ") -> IP6 | E41: CMBC | F41: Rob | G41: Ric AM | J41: y | K41: Debenn inns - with rob to email | M41: lead low | N41: fu rm - top 20
A42: The Grebe | B42: NR12 9BB | C42: =LEFT(B42,2) -> NR | D42: =_xlfn.TEXTBEFORE(B42, " ") -> NR12 | E42: CMBC | G42: steve and steve | M42: lead mid | N42: sdm quote - delay!
A43: Three Bottles | B43: CO9 4HY | E43: admiral | F43: mciver | K43: pale churning? Mahou ipo cask? …mciver | L43: mahou | M43: lead mid
A44: Victoriia | B44: ip22 4hw | E44: gk ift | G44: andre | I44: 7917 223165 | M44: install fu
A45: White Horse | B45: CO10 1RF | C45: =LEFT(B45,2) -> CO | D45: =_xlfn.TEXTBEFORE(B45, " ") -> CO10 | E45: GK L&T | F45: Sam | G45: Gary and Ashley | J45: y | K45: wants rid of icebreaker and will swap anything for a bribe (wants a canopy for outside at min covered with parasols) bud is great for him amd better than Foster, target proud of his 0 offerings and adding huk 0 if I don't do my job well lol research beers at other pubs as want to be different and thinks weavers has camden (they dont) . fu meeting next week pre opwning | M45: protect | N45: (CALL WIFE AT SWAN co10 9jq 1ST)
A46: white horse | B46: nr14 8st | C46: =LEFT(B46,2) -> nr | D46: =_xlfn.TEXTBEFORE(B46, " ") -> nr14 | E46: punch | F46: mark neild | G46: charlotte&mike | I46: 7475418263 | K46: murphy/guinnes (on a year and both doing swell-stout ops) - only 0 and fruit cider in fridge | L46: stout | M46: lead mid
A47: White Horse Upton | B47: NR13 6BT | C47: =LEFT(B47,2) -> NR | D47: =_xlfn.TEXTBEFORE(B47, " ") -> NR13 | E47: GK IFT | F47: adam vass | G47: miss hood | K47: large garden, events and music and food focused, removed peroni and madri for stella and san mig. ops for fruit cider. Mrs hood contact best for late afternoons. missing stella pint order, resending | M47: install fu | N47: tnt op?
A48: Wick Lodge | B48: CO16 8BG | C48: =LEFT(B48,2) -> CO | D48: =_xlfn.TEXTBEFORE(B48, " ") -> CO16 | E48: CMBC | F48: Nikki | G48: Danny | H48: thewicklodge@gmail.com | K48: met owners daughter, passed on Danny's email. only in weekends and said she would hound him for a meet. she's unsure if still cmbc supplied, but doesn't want tnt clientel. | M48: lead low
A49: Yachtsmans Arms | B49: CO7 0AZ | C49: =LEFT(B49,2) -> CO | D49: =_xlfn.TEXTBEFORE(B49, " ") -> CO7 | E49: GK L&T | F49: Pearson | G49: Natalie & Phil? | K49: stella best fit. well up for switcheroo to try things. peroni bigg3st cost but sells well amd only pub in town with it. no Stella ops, feels her older clientel have the wife beater stuck in theor head, and is all over town. madri does a hit and miss and is up for san mig, wants rm to quote her and likely will move forward. hells and kop ops for summer. small cellar, no extra tap, would replace aspall and peroni if dips (hasn't seen a rep in ages) | L49: Stella | M49: lead low

Sheet TopVol
A1: RTM | B1: POC | C1: Zip | D1: Brand(s) | E1: 2025 TTL VOL | F1: Volume YoY | G1: Group? | H1: DM | I1: Notes | J1: TODO
A2: GK IFT | B2: White Horse (Corton) | C2: NR32 5HP | D2: 10gl Stella Artois 4.6, 11G 50L San Miguel Grundy 5.0 | E2: 92.3446 | H2: Lisa (tasha AM) | I2: wee bit out of the way to drive to. 2max kegs a week per brand. carling, aspall, target.. add with tnt ops. more cafe restraunt clientel | J2: tnt
A3: GK IFT | B3: Potters Leisure Ltd (Gt Yarmouth) | C3: NR31 9BX | D3: 10gl Stella Artois 4.6 11G/50L Becks Vier 4.0 11G/50L Budweiser Draught 4.5 | E3: 467.5726 | J3: never visited
A4: GK IFT | B4: Number 1 Bar & Kitchen (Gorleston) | C4: NR31 6DA | D4: 10gl Stella Artois 4.6 11G/50L Budweiser Draught 4.5 11G/50L San Miguel Grundy 5.0 | E4: 116.8384 | I4: SDM just asked for foc for cheap stella jan deal | J4: …fraser foc call sdm
A5: GK IFT | B5: Norwich City Football Club (Norwich | C5: NR1 1JE | D5: 11G/50L Camden Hells Lager 4.6 30ltr Kopparberg Strawb & Lime 4.0 | E5: 204.3 | I5: SDM Neil deals with, do reach out to support
A6: GK IFT | B6: Little Wellington (Stowmarket) | C6: IP14 5AG | D6: 10gl Stella Artois 4.6 11G/50L San Miguel Grundy 5.0 | E6: 96.0568 | H6: Pete (AKA FRIDGE) | I6: unlikely ops. Brands swell. Not tnt want of vianet tracking
A7: GK IFT | B7: Kings Arms Hotel (North Walsham) | C7: NR28 9JX | D7: 10gl Stella Artois 4.6 11G/50L Camden Hells Lager 4.6 11G/50L San Miguel Grundy 5.0 | E7: 153.0314 | H7: Sarah (dad Martin Miles) | I7: gk stole from lacons, sdm ticked off at wam. Hates lacons cellar serivces
A8: GK IFT | B8: Jolly Sailors (Lowestoft) | C8: NR33 0JS | D8: 10gl Stella Artois 4.6 30ltr Camden Hells Lager 4.6 11G/50L Bud Light 3.4 11G/50L San Miguel Grundy 5.0 | E8: 171.686 | G8: Moss & Co | H8: adam mngr sarah am
A9: GK IFT | B9: JD Young Hotel (Harleston) | C9: IP20 9AD | D9: 10gl Stella Artois 4.6 11G/50L Bud Light 3.4 11G/50L San Miguel Grundy 5.0 | E9: 127.3268 | H9: beth owner, Ella mngr | I9: doesn’t want team to know white label is BL. Agreed listing fee with sdm, no one answered to sign… asked for tnt? Sorted? Oooold | J9: listing fee
A10: GK IFT | B10: Frinton On Sea War Memorial Club | C10: CO13 9EB | D10: 10gl Stella Artois 4.6 11G/50L San Miguel Grundy 5.0 | E10: 102.2356 | J10: never visited
A11: GK IFT | B11: Flying Horse Inn (Ipswich) | C11: IP1 5NW | D11: 30ltr Kopparberg Strawb & Lime 4.0 11G/50L San Miguel Grundy 5.0 | E11: 90.3 | H11: Sarah (gareth tender) | I11: SM Top vol and kop top 2. has tnt. Low ops, mostly gk
A12: GK IFT | B12: Falgate Arms (Hiegham) | C12: NR29 5HZ | D12: 10gl Stella Artois 4.6 11G/50L San Miguel Grundy 5.0 | E12: 90.1592 | J12: never visited
A13: GK IFT | B13: Edinburgh Inn (Wells Next to the | C13: NR23 1AE | D13: 10gl Stella Artois 4.6 | E13: 91.8264 | H13: Michael? (jack tender) | I13: 'cheapest pub in cromer'
A14: GK IFT | B14: Eaton Cottage (Norwich) | C14: NR2 2DQ | D14: 10gl Stella Artois 4.6 11G/50L San Miguel Grundy 5.0 | E14: 103.1262 | H14: Phil | I14: mostly gk, small pub, maybe kop opps, nice guy but never comes down just phone. (asked for parasols at one point, told sdm only if he actually meets me and ops)
A15: GK IFT | B15: Crossways Inn Scole Ltd (Scole) | C15: IP21 4DP | D15: 10gl Stella Artois 4.6 11G/50L Becks Vier 4.0 | E15: 91.1874 | H15: Scott | I15: massive place, gorgeous garden, on gk list but with no bbg and becks is pouring- lacons, cmbc, gk - Hells ipo cruz ops | J15: op
A16: GK IFT | B16: Cliff Quay Brewery (Debenham) | C16: IP14 6RP | D16: 10gl Stella Artois 4.6 11G/50L San Miguel Grundy 5.0 | E16: 112.4046 | J16: never visited
A17: GK IFT | B17: Brewer Arms (Brightlingsea) | C17: CO7 0BX | D17: 10gl Stella Artois 4.6 11G/50L San Miguel Grundy 5.0 | E17: 116.0142 | H17: julie ll and maddie tender | I17: tnt ops- is price why they don't have and will share with julie the 50% | J17: tnt
A18: GK IFT | B18: Gorleston Golf Club (Gorleston) | C18: NR31 6JT | D18: 11G/50L Budweiser Draught 4.5 11G/50L San Miguel Grundy 5.0 | E18: 87.5 | J18: never visited
A19: GK IFT | B19: Fishing Boat (East Runton) | C19: NR27 9NX | D19: 10gl Stella Artois 4.6 11G/50L San Miguel Grundy 5.0 | E19: 85.5996 | H19: Sue
A20: GK IFT | B20: Epic Studios (Norwich) | C20: NR3 1JD | D20: 10gl Stella Artois 4.6 | E20: 84.289 | I20: late opening, emailed late 2024 for meet, responded but never responded to book.
A21: GK IFT | B21: Darbys (Swanton) | C21: NR20 4NY | D21: 10gl Stella Artois 4.6 11G/50L Camden Hells Lager 4.6 | E21: 82.9322 | H21: Collin | I21: listing fee running out.
A22: Greene King L&T | B22: Crown | C22: CO10 0AT | D22: San Miguel Stella Artois | E22: 45.828914 | F22: 0.93912511 | I22: San miguel new? Not visited since may 2024
A23: Admiral | B23: Lion | C23: CO10 8HP | D23: Stella Artois | E23: 46.337347 | F23: 1.8101429 | H23: Carmen & Sarah? 07951066228 (Facebook) | I23: never visited
A24: Admiral | B24: Trafalgar | C24: CO12 4LW | D24: San Miguel Stella Artois | E24: 121 | F24: 0.30754338 | H24: Joanne ? 07949839114 (facebook) | I24: Never visited
A25: Admiral | B25: Queens Head Hotel | C25: CO14 8AD | D25: San Miguel Stella Artois | E25: 110 | F25: 0.85365135 | H25: Jane
A26: Greene King L&T | B26: Victory | C26: CO14 8AR | D26: Stella Artois | E26: 32 | F26: Infinity | H26: Emma | I26: San Miguel op with time
A27: Stonegate | B27: Three Jays | C27: CO15 2PJ | D27: Stella Artois Corona Extra | E27: 32 | F27: Infinity | H27: Adrian | I27: Corona on for TNT, joined stella. Rona not doing great, awesome dude, lots of talking. Likely swap rona for sm early 2026. hates huk reps. Plenty of lines
A28: Admiral | B28: Silver Oyster | C28: CO2 8LY | D28: San Miguel | E28: 122.93591 | F28: 0.48301764 | G28: Yes Gallo IFT -The Grapes down the road | H28: Pet & Ami | I28: Next to no ops at Grapes, very low Pale ops ipo neckoil. Listing Fee not enough $$ for increase kegs
A29: Admiral | B29: Brewers Arms | C29: IP1 3NS | D29: Camden Pale Ale Stella Artois | E29: 92 | F29: -0.16233403 | G29: yes Walnute IP14 | H29: Andy (steve partner) | I29: Brands safe, low ops, less SM/Mahou $ against madri
A30: Trust | B30: Royal Oak | C30: IP13 8DH | D30: Becks | E30: 38 | F30: 11.667 | H30: Leanne & Bob est Dec 2024? Facebook | I30: never visited
A31: Greene King L&T | B31: Crown Hotel | C31: IP13 9AP | D31: San Miguel Camden Hells | E31: 37 | F31: 4.095 | H31: Chris | I31: Kopp opps with time. Hells on forever, lost to GK, returned last year ipo aspall
A32: Greene King L&T | B32: Station Hotel | C32: IP2 8AJ | D32: San Miguel Kopparberg Straw & Lime Camden Hells | E32: 99.507756 | F32: Infinity | H32: James | I32: low ops, maybe pale/stella. Huge soccer volume, invested with tables. Class dude, support
A33: Stonegate | B33: Wortwell Bell | C33: IP20 0HH | D33: Becks Stella Artois Camden Hells Kopparberg Straw & Lime | E33: 41.629259 | F33: 0.60605263 | G33: yes | H33: Keighly | I33: awesome lady, goodluck booking in. x3 sites (x2 SG, x1 Lacons - all bbg). Support. Interest in tnt but no movement. Removed sky $$
A34: Admiral | B34: Albion | C34: IP24 2DN | D34: San Miguel Stella Artois | E34: 116 | F34: 0.74868442 | H34: Shawn (lawrence mngr) | I34: Lost Stella.
A35: Admiral | B35: Margaret Catchpole Inn | C35: IP3 0PQ | D35: Stella Artois | E35: 42.691077 | F35: -0.060195094 | H35: Shona | I35: Stella safe on churn, but hurting on business - loves stella but $ fears. Up for pale/kop but $
A36: Punch | B36: Golden Hind | C36: IP3 9NF | D36: San Miguel | E36: 54.808362 | F36: 15.606571 | H36: Ryan | I36: lost stout to murphy-sales nil ops, less hells returns
A37: Greene King L&T | B37: Fox | C37: IP30 9HD | D37: Stella Artois Becks | E37: 55.869672 | F37: -0.15061872 | H37: Jimmy | I37: unlikely ops. Embarrasing ift/lt tnt and listing fee situ? Still support, decent vol, was open to SM with $$ and tnt
A38: Admiral | B38: Gardeners Arms | C38: IP30 9PA | D38: San Miguel Camden Hells | E38: 73.963115 | F38: 0.48051786 | H38: Martin & Claire | I38: new ll, friends with Roly at Chestnut. Gave donation of Belfry tix. Pale pushing but $
A39: Admiral | B39: Dun Cow | C39: IP31 1AA | D39: Stella Artois San Miguel | E39: 33 | F39: 1.753 | H39: Kev | I39: ift ops light. Cider maybe? San miguel issues
A40: Greene King L&T | B40: Woolpack | C40: IP31 1SW | D40: San Miguel | E40: 36 | F40: Infinity | H40: Graham | I40: I good complainer about GK and $. SM safe. Knows the old kop owner? Kop ops,. Hells could be an option ipo gamma (but 'everything is good' and $) also has an IFT site in town, never open
A41: Greene King L&T | B41: Pykkerell Inn | C41: IP31 2HH | D41: San Miguel Stella Artois | E41: 33 | F41: 0.375 | H41: Lesley | I41: google says Closed down? Lesely uninterested in talking. Only ops is cider/foster maybe
A42: Punch | B42: Bell Inn | C42: IP5 1AA | D42: Stella Artois | E42: 77.284165 | F42: -0.11458333 | H42: Sam and deb
A43: Punch | B43: Greyhound Inn | C43: IP6 0AR | D43: Stella Artois | E43: 44.552048 | F43: 0.020833333 | H43: Rachel | I43: nicest punch pub around, friendly staff, not so interested dm in 2024
A44: Greene King L&T | B44: Huntsman | C44: NR13 4BH | D44: San Miguel Camden Hells | E44: 30 | F44: Infinity | I44: Never Visited
A45: Stonegate | B45: Gibraltar Gardens | C45: NR2 4LZ | D45: Stella Artois Camden Hells Camden Pale | E45: 39 | F45: Infinity | H45: Dave and Kim | I45: you owe them a mural and a billion camden parasols…. Harry
A46: Stonegate | B46: Prince Regent | C46: NR30 2AJ | D46: Stella Artois | E46: 45.006893 | F46: -0.042569183 | H46: Alison & Trevor | I46: booked and no showed in oct. turned craft union? Sm ipo madri target
A47: Admiral | B47: Golfers Arms | C47: NR30 4LU | D47: Stella Artois | E47: 32 | F47: 0.259 | H47: Chris (dionne tender) | I47: San Mig ops (cruz dummy forever)
A48: Admiral | B48: Flying Dutchman | C48: NR33 8QS | D48: Stella Artois | E48: 109.42892 | F48: -0.032344622 | H48: Chris | I48: Unlikely-RM aid, wants kopp, up for pale ipo neckoil but not cheaper any more… easy?
A49: Stonegate | B49: SP Oak Tree Norwich | C49: NR4 6LA | D49: San Miguel Corona Extra Camden Hells Camden Pale Ale | E49: 42.504538 | F49: 41.497969 | G49: Stout & Stone Inns | H49: danny ops mngr, Mia am | I49: spoke with Mia mngr on, danny is operations onsite guy. Camden hells swapped for corona and pale for redstripe. pale was more affordable amd sold waaay better
A50: Punch | B50: Norkie | C50: NR5 9HA | D50: San Miguel Stella Artois | E50: 69.646907 | F50: 1.1823442 | H50: Steve (Dionne & Gracie (mngr/daughter)) | I50: never met steve, just ladies. No stout ops, SM if returns
A51: Stonegate | B51: Cottage | C51: NR7 0JD | D51: San Miguel Corona Extra | E51: 41.004884 | F51: Infinity | H51: ian | I51: sm delist, swapped for rona. Little ops, hoping stella/hells with time. Light interest in leffe but wont be high sales

Sheet Q1 Churn
A1: Outlet Name | B1: Outlet Postcode | C1: Estate Type | D1: Strike | E1: Distribution in Strike | F1: Brand(s) | G1: Volume YTD | H1: Notes
A2: Angel Sudbury | B2: CO10 2AG | C2: L&T | D2: 1 | E2: 1 | F2: Camden Pale | G2: 2.5003455
A3: Barley Mow Inn | B3: IP6 9EH | C3: L&T | D3: 1 | E3: 1 | F3: Camden Pale | G3: 24.383465
A4: Belle Aire | B4: NR29 4HS | C4: Free Trade | D4: 1 | E4: 1 | F4: San Miguel | G4: 25.280109
A5: Birch Grove Golf Course | B5: CO2 0HS | C5: Free Trade | D5: 1 | E5: 2 | F5: San Miguel Stella Artois | G5: 19.748382
A6: Black Swan | B6: NR10 3HJ | C6: Free Trade | D6: 1 | E6: 2 | F6: Stella Artois San Miguel | G6: 15.779486
A7: Claydon & Barham Social Club & Com | B7: IP6 0EG | C7: Free Trade | D7: 1 | E7: 1 | F7: San Miguel | G7: 7.0146919
A8: Colne Valley Golf Club | B8: CO6 2LT | C8: Free Trade | D8: 1 | E8: 1 | F8: San Miguel | G8: 14.502317
A9: Comfortable Cow | B9: CO10 2EB | C9: Free Trade | D9: 1 | E9: 1 | F9: Stella Artois | G9: 21.422186
A10: Curve Bar | B10: IP1 1RJ | C10: Free Trade | D10: 1 | E10: 1 | F10: San Miguel | G10: 29.004006
A11: Donkey And Buskins | B11: CO2 0HU | C11: Free Trade | D11: 1 | E11: 1 | F11: San Miguel | G11: 29.991626
A12: Duke Of York | B12: IP4 2QP | C12: Free Trade | D12: 1 | E12: 2 | F12: Camden Pale San Miguel | G12: 49.509713
A13: East Coast Bars | B13: NR9 4LF | C13: Free Trade | D13: 1 | E13: 1 | F13: Camden Hells | G13: 41.906698
... A40: Thatch Restaurant (Lowestoft) | B40: NR33 0BY | C40: Free Trade | D40: 1 | E40: 1 | F40: San Miguel | G40: 5.4983249
A41: The Cricketers | B41: NR11 7AA | C41: Free Trade | D41: 1 | E41: 1 | F41: Stella Artois Unfiltered | G41: 66.199195 | H41: not gk - wam?
A42: The Lady Elizabeth | B42: CO10 2EA | C42: L&T | D42: 1 | E42: 1 | F42: San Miguel | G42: 14.502327
A43: Thetford Rugby Club | B43: IP24 1NB | C43: Free Trade | D43: 1 | E43: 1 | F43: Stella Artois | G43: 3.6385396
A44: Three Bottles Inn | B44: CO9 4HY | C44: L&T | D44: 1 | E44: 1 | F44: Camden Hells | G44: 84.826687
A45: Three Tuns | B45: IP6 8AA | C45: Free Trade | D45: 1 | E45: 1 | F45: San Miguel | G45: 52.305402
A46: Twisters | B46: CO1 1PY | C46: Free Trade | D46: 1 | E46: 1 | F46: Camden Hells | G46: 4.5073467
A47: Village Maid | B47: CO11 2UU | C47: Free Trade | D47: 1 | E47: 1 | F47: Stella Artois | G47: 28.650024
A48: Vulcan Arms | B48: IP16 4UD | C48: Free Trade | D48: 1 | E48: 1 | F48: San Miguel | G48: 3.5073459
A49: White Horse | B49: NR14 8ST | C49: L&T | D49: 1 | E49: 1 | F49: San Miguel | G49: 8.4558369
A50: Windmill | B50: NR3 2RE | C50: Free Trade | D50: 1 | E50: 1 | F50: San Miguel | G50: 23.880766
A51: Blue Boar Inn | B51: IP31 3AA | C51: Free Trade | D51: 2 | E51: 1 | F51: San Miguel | G51: 38.406907
A52: Broad Farm Caravan Site | B52: NR29 3AT | C52: Free Trade | D52: 2 | E52: 2 | F52: Budlight San Miguel | G52: 28.502081
A53: Chilton Fields Sports Club | B53: IP14 1LB | C53: Free Trade | D53: 2 | E53: 1 | F53: San Miguel | G53: 29.327716
... A70: Wolf Inn Lowestoft | B70: NR32 3LN | C70: Free Trade | D70: 2 | E70: 1 | F70: Stella Artois | G70: 6.8134216

Sheet Modelo & Eazy Target List
A1: rtm | B1: outlet_name | C1: street_address | D1: town | E1: postcode_outward | F1: postcode_inward | G1: Modelo or Eazy (ros 50l a wk, most $ tap?) | H1: notes
A2: Stonegate | B2: Ferry Inn & Cafe | C2: The Ferry | D2: Felixstowe | E2: IP11 | F2: 9RZ | G2: MODELO | H2: sm delist. swapped for peroni. harry seems gone as tender didn't recognise him amd said call land line gorge location off ocean and golf course.
A3: Stonegate | B3: Gibraltor Gardens | E3: NR2 | F3: 4LZ | G3: MODELO | H3: pending owed investment, likely no until then - but great location
A4: Stonegate | B4: Belle Vue | E4: NR4 | F4: 7AB | G4: MODELO | H4: BOOK MEET
A5: Stonegate | B5: Cottage | E5: NR7 | F5: 0JD | G5: MODELO | H5: possible, book
